Workbook

Sheet Dashboard
B1: Amazon Sales Performance Dashboard
B2: September 2026 order data | Use the yellow dropdowns to filter | Amounts in ₹
B4: Category | C4: All | D4: Customer Location | E4: All | G4: Order Status | H4: All | I4: Month | J4: All
B6: Total Sales | C6: Total Orders | D6: Units Sold | E6: Avg Order Value | F6: Delivered % | G6: Cancelled % | H6: Pending %
B7: =SUMIFS(Cleaned_Data!$G$2:$G$501,Cleaned_Data!$D$2:$D$501,Pivots!$B$3,Cleaned_Data!$I$2:$I$501,Pivots!$B$4,Cleaned_Data!$N$2:$N$501,Pivots!$B$5,Cleaned_Data!$L$2:$L$501,Pivots!$B$6) -> 1564790 | C7: =COUNTIFS(Cleaned_Data!$D$2:$D$501,Pivots!$B$3,Cleaned_Data!$I$2:$I$501,Pivots!$B$4,Cleaned_Data!$N$2:$N$501,Pivots!$B$5,Cleaned_Data!$L$2:$L$501,Pivots!$B$6) -> 500 | D7: =SUMIFS(Cleaned_Data!$F$2:$F$501,Cleaned_Data!$D$2:$D$501,Pivots!$B$3,Cleaned_Data!$I$2:$I$501,Pivots!$B$4,Cleaned_Data!$N$2:$N$501,Pivots!$B$5,Cleaned_Data!$L$2:$L$501,Pivots!$B$6) -> 810 | E7: =IF(C7=0,0,B7/C7) -> 3129.58 | F7: =IF(COUNTIFS(Cleaned_Data!$D$2:$D$501,Pivots!$B$3,Cleaned_Data!$I$2:$I$501,Pivots!$B$4,Cleaned_Data!$L$2:$L$501,Pivots!$B$6)=0,0,COUNTIFS(Cleaned_Data!$D$2:$D$501,Pivots!$B$3,Cleaned_Data!$I$2:$I$501,Pivots!$B$4,Cleaned_Data!$L$2:$L$501,Pivots!$B$6,Cleaned_Data!$N$2:$N$501,"Delivered")/COUNTIFS(Cleaned_Data!$D$2:$D$501,Pivots!$B$3,Cleaned_Data!$I$2:$I$501,Pivots!$B$4,Cleaned_Data!$L$2:$L$501,Pivots!$B$6)) -> 0.764 | G7: =IF(COUNTIFS(Cleaned_Data!$D$2:$D$501,Pivots!$B$3,Cleaned_Data!$I$2:$I$501,Pivots!$B$4,Cleaned_Data!$L$2:$L$501,Pivots!$B$6)=0,0,COUNTIFS(Cleaned_Data!$D$2:$D$501,Pivots!$B$3,Cleaned_Data!$I$2:$I$501,Pivots!$B$4,Cleaned_Data!$L$2:$L$501,Pivots!$B$6,Cleaned_Data!$N$2:$N$501,"Cancelled")/COUNTIFS(Cleaned_Data!$D$2:$D$501,Pivots!$B$3,Cleaned_Data!$I$2:$I$501,Pivots!$B$4,Cleaned_Data!$L$2:$L$501,Pivots!$B$6)) -> 0.126 | H7: =IF(COUNTIFS(Cleaned_Data!$D$2:$D$501,Pivots!$B$3,Cleaned_Data!$I$2:$I$501,Pivots!$B$4,Cleaned_Data!$L$2:$L$501,Pivots!$B$6)=0,0,COUNTIFS(Cleaned_Data!$D$2:$D$501,Pivots!$B$3,Cleaned_Data!$I$2:$I$501,Pivots!$B$4,Cleaned_Data!$L$2:$L$501,Pivots!$B$6,Cleaned_Data!$N$2:$N$501,"Pending")/COUNTIFS(Cleaned_Data!$D$2:$D$501,Pivots!$B$3,Cleaned_Data!$I$2:$I$501,Pivots!$B$4,Cleaned_Data!$L$2:$L$501,Pivots!$B$6)) -> 0.11

Sheet Pivots
A1: Pivot Tables (formula-driven; respond to the Dashboard filters)
A3: Category criteria | B3: =IF(Dashboard!$C$4="All","*",Dashboard!$C$4) -> * | C3: '*' = All (wildcard). Set by the dropdowns on the Dashboard.
A4: Location criteria | B4: =IF(Dashboard!$E$4="All","*",Dashboard!$E$4) -> *
A5: Status criteria | B5: =IF(Dashboard!$H$4="All","*",Dashboard!$H$4) -> *
A6: Month criteria | B6: =IF(Dashboard!$J$4="All","*",Dashboard!$J$4) -> *
A9: Category-wise Total Sales | I9: Top 10 Customers by Total Spending
A10: Item | B10: Total Sales | C10: Orders | D10: Units Sold | E10: % of Sales | F10: Total Sales (all data) | I10: Rank | J10: Customer | K10: Total Sales | L10: Orders
A11: Electronics | B11: =SUMIFS(Cleaned_Data!$G$2:$G$501,Cleaned_Data!$D$2:$D$501,$A11,Cleaned_Data!$I$2:$I$501,$B$4,Cleaned_Data!$N$2:$N$501,$B$5,Cleaned_Data!$L$2:$L$501,$B$6) -> 595070 | C11: =COUNTIFS(Cleaned_Data!$D$2:$D$501,$A11,Cleaned_Data!$I$2:$I$501,$B$4,Cleaned_Data!$N$2:$N$501,$B$5,Cleaned_Data!$L$2:$L$501,$B$6) -> 148 | D11: =SUMIFS(Cleaned_Data!$F$2:$F$501,Cleaned_Data!$D$2:$D$501,$A11,Cleaned_Data!$I$2:$I$501,$B$4,Cleaned_Data!$N$2:$N$501,$B$5,Cleaned_Data!$L$2:$L$501,$B$6) -> 230 | E11: =IF($B$16=0,0,B11/$B$16) -> 0.38028745 | F11: =SUMIFS(Cleaned_Data!$G$2:$G$501,Cleaned_Data!$D$2:$D$501,$A11) -> 595070 | I11: 1 | J11: =INDEX($A$73:$A$132,MATCH(LARGE($G$73:$G$132,I11),$G$73:$G$132,0)) -> Anjali Verma | K11: =INDEX($B$73:$B$132,MATCH(LARGE($G$73:$G$132,I11),$G$73:$G$132,0)) -> 59983 | L11: =INDEX($C$73:$C$132,MATCH(LARGE($G$73:$G$132,I11),$G$73:$G$132,0)) -> 9
A12: Home & Kitchen | B12: =SUMIFS(Cleaned_Data!$G$2:$G$501,Cleaned_Data!$D$2:$D$501,$A12,Cleaned_Data!$I$2:$I$501,$B$4,Cleaned_Data!$N$2:$N$501,$B$5,Cleaned_Data!$L$2:$L$501,$B$6) -> 416310 | C12: =COUNTIFS(Cleaned_Data!$D$2:$D$501,$A12,Cleaned_Data!$I$2:$I$501,$B$4,Cleaned_Data!$N$2:$N$501,$B$5,Cleaned_Data!$L$2:$L$501,$B$6) -> 113 | D12: =SUMIFS(Cleaned_Data!$F$2:$F$501,Cleaned_Data!$D$2:$D$501,$A12,Cleaned_Data!$I$2:$I$501,$B$4,Cleaned_Data!$N$2:$N$501,$B$5,Cleaned_Data!$L$2:$L$501,$B$6) -> 190 | E12: =IF($B$16=0,0,B12/$B$16) -> 0.26604848 | F12: =SUMIFS(Cleaned_Data!$G$2:$G$501,Cleaned_Data!$D$2:$D$501,$A12) -> 416310 | I12: 2 | J12: =INDEX($A$73:$A$132,MATCH(LARGE($G$73:$G$132,I12),$G$73:$G$132,0)) -> Vikram Nair | K12: =INDEX($B$73:$B$132,MATCH(LARGE($G$73:$G$132,I12),$G$73:$G$132,0)) -> 53281 | L12: =INDEX($C$73:$C$132,MATCH(LARGE($G$73:$G$132,I12),$G$73:$G$132,0)) -> 11
A13: Footwear | B13: =SUMIFS(Cleaned_Data!$G$2:$G$501,Cleaned_Data!$D$2:$D$501,$A13,Cleaned_Data!$I$2:$I$501,$B$4,Cleaned_Data!$N$2:$N$501,$B$5,Cleaned_Data!$L$2:$L$501,$B$6) -> 356943 | C13: =COUNTIFS(Cleaned_Data!$D$2:$D$501,$A13,Cleaned_Data!$I$2:$I$501,$B$4,Cleaned_Data!$N$2:$N$501,$B$5,Cleaned_Data!$L$2:$L$501,$B$6) -> 97 | D13: =SUMIFS(Cleaned_Data!$F$2:$F$501,Cleaned_Data!$D$2:$D$501,$A13,Cleaned_Data!$I$2:$I$501,$B$4,Cleaned_Data!$N$2:$N$501,$B$5,Cleaned_Data!$L$2:$L$501,$B$6) -> 157 | E13: =IF($B$16=0,0,B13/$B$16) -> 0.2281092 | F13: =SUMIFS(Cleaned_Data!$G$2:$G$501,Cleaned_Data!$D$2:$D$501,$A13) -> 356943 | I13: 3 | J13: =INDEX($A$73:$A$132,MATCH(LARGE($G$73:$G$132,I13),$G$73:$G$132,0)) -> Ishaan Chopra | K13: =INDEX($B$73:$B$132,MATCH(LARGE($G$73:$G$132,I13),$G$73:$G$132,0)) -> 50384 | L13: =INDEX($C$73:$C$132,MATCH(LARGE($G$73:$G$132,I13),$G$73:$G$132,0)) -> 9
A14: Clothing | B14: =SUMIFS(Cleaned_Data!$G$2:$G$501,Cleaned_Data!$D$2:$D$501,$A14,Cleaned_Data!$I$2:$I$501,$B$4,Cleaned_Data!$N$2:$N$501,$B$5,Cleaned_Data!$L$2:$L$501,$B$6) -> 136083 | C14: =COUNTIFS(Cleaned_Data!$D$2:$D$501,$A14,Cleaned_Data!$I$2:$I$501,$B$4,Cleaned_Data!$N$2:$N$501,$B$5,Cleaned_Data!$L$2:$L$501,$B$6) -> 70 | D14: =SUMIFS(Cleaned_Data!$F$2:$F$501,Cleaned_Data!$D$2:$D$501,$A14,Cleaned_Data!$I$2:$I$501,$B$4,Cleaned_Data!$N$2:$N$501,$B$5,Cleaned_Data!$L$2:$L$501,$B$6) -> 117 | E14: =IF($B$16=0,0,B14/$B$16) -> 0.086965663 | F14: =SUMIFS(Cleaned_Data!$G$2:$G$501,Cleaned_Data!$D$2:$D$501,$A14) -> 136083 | I14: 4 | J14: =INDEX($A$73:$A$132,MATCH(LARGE($G$73:$G$132,I14),$G$73:$G$132,0)) -> Kavya Rao | K14: =INDEX($B$73:$B$132,MATCH(LARGE($G$73:$G$132,I14),$G$73:$G$132,0)) -> 45980 | L14: =INDEX($C$73:$C$132,MATCH(LARGE($G$73:$G$132,I14),$G$73:$G$132,0)) -> 10
A15: Books | B15: =SUMIFS(Cleaned_Data!$G$2:$G$501,Cleaned_Data!$D$2:$D$501,$A15,Cleaned_Data!$I$2:$I$501,$B$4,Cleaned_Data!$N$2:$N$501,$B$5,Cleaned_Data!$L$2:$L$501,$B$6) -> 60384 | C15: =COUNTIFS(Cleaned_Data!$D$2:$D$501,$A15,Cleaned_Data!$I$2:$I$501,$B$4,Cleaned_Data!$N$2:$N$501,$B$5,Cleaned_Data!$L$2:$L$501,$B$6) -> 72 | D15: =SUMIFS(Cleaned_Data!$F$2:$F$501,Cleaned_Data!$D$2:$D$501,$A15,Cleaned_Data!$I$2:$I$501,$B$4,Cleaned_Data!$N$2:$N$501,$B$5,Cleaned_Data!$L$2:$L$501,$B$6) -> 116 | E15: =IF($B$16=0,0,B15/$B$16) -> 0.038589204 | F15: =SUMIFS(Cleaned_Data!$G$2:$G$501,Cleaned_Data!$D$2:$D$501,$A15) -> 60384 | I15: 5 | J15: =INDEX($A$73:$A$132,MATCH(LARGE($G$73:$G$132,I15),$G$73:$G$132,0)) -> Rajesh Reddy | K15: =INDEX($B$73:$B$132,MATCH(LARGE($G$73:$G$132,I15),$G$73:$G$132,0)) -> 44481 | L15: =INDEX($C$73:$C$132,MATCH(LARGE($G$73:$G$132,I15),$G$73:$G$132,0)) -> 9
A16: Grand Total | B16: =SUM(B11:B15) -> 1564790 | C16: =SUM(C11:C15) -> 500 | D16: =SUM(D11:D15) -> 810 | E16: =SUM(E11:E15) -> 1 | F16: =SUM(F11:F15) -> 1564790 | I16: 6 | J16: =INDEX($A$73:$A$132,MATCH(LARGE($G$73:$G$132,I16),$G$73:$G$132,0)) -> Aditya Iyer | K16: =INDEX($B$73:$B$132,MATCH(LARGE($G$73:$G$132,I16),$G$73:$G$132,0)) -> 40576 | L16: =INDEX($C$73:$C$132,MATCH(LARGE($G$73:$G$132,I16),$G$73:$G$132,0)) -> 12
I17: 7 | J17: =INDEX($A$73:$A$132,MATCH(LARGE($G$73:$G$132,I17),$G$73:$G$132,0)) -> Nikhil Joshi | K17: =INDEX($B$73:$B$132,MATCH(LARGE($G$73:$G$132,I17),$G$73:$G$132,0)) -> 39683 | L17: =INDEX($C$73:$C$132,MATCH(LARGE($G$73:$G$132,I17),$G$73:$G$132,0)) -> 10
I18: 8 | J18: =INDEX($A$73:$A$132,MATCH(LARGE($G$73:$G$132,I18),$G$73:$G$132,0)) -> Sahil Sharma | K18: =INDEX($B$73:$B$132,MATCH(LARGE($G$73:$G$132,I18),$G$73:$G$132,0)) -> 39477 | L18: =INDEX($C$73:$C$132,MATCH(LARGE($G$73:$G$132,I18),$G$73:$G$132,0)) -> 12
A19: Product-wise Performance | I19: 9 | J19: =INDEX($A$73:$A$132,MATCH(LARGE($G$73:$G$132,I19),$G$73:$G$132,0)) -> Tanvi Iyer | K19: =INDEX($B$73:$B$132,MATCH(LARGE($G$73:$G$132,I19),$G$73:$G$132,0)) -> 39288 | L19: =INDEX($C$73:$C$132,MATCH(LARGE($G$73:$G$132,I19),$G$73:$G$132,0)) -> 8
A20: Item | B20: Total Sales | C20: Orders | D20: Units Sold | E20: % of Sales | F20: Total Sales (all data) | I20: 10 | J20: =INDEX($A$73:$A$132,MATCH(LARGE($G$73:$G$132,I20),$G$73:$G$132,0)) -> Nikhil Rao | K20: =INDEX($B$73:$B$132,MATCH(LARGE($G$73:$G$132,I20),$G$73:$G$132,0)) -> 37782 | L20: =INDEX($C$73:$C$132,MATCH(LARGE($G$73:$G$132,I20),$G$73:$G$132,0)) -> 10
A21: Smart Watch | B21: =SUMIFS(Cleaned_Data!$G$2:$G$501,Cleaned_Data!$C$2:$C$501,$A21,Cleaned_Data!$D$2:$D$501,$B$3,Cleaned_Data!$I$2:$I$501,$B$4,Cleaned_Data!$N$2:$N$501,$B$5,Cleaned_Data!$L$2:$L$501,$B$6) -> 234953 | C21: =COUNTIFS(Cleaned_Data!$C$2:$C$501,$A21,Cleaned_Data!$D$2:$D$501,$B$3,Cleaned_Data!$I$2:$I$501,$B$4,Cleaned_Data!$N$2:$N$501,$B$5,Cleaned_Data!$L$2:$L$501,$B$6) -> 33 | D21: =SUMIFS(Cleaned_Data!$F$2:$F$501,Cleaned_Data!$C$2:$C$501,$A21,Cleaned_Data!$D$2:$D$501,$B$3,Cleaned_Data!$I$2:$I$501,$B$4,Cleaned_Data!$N$2:$N$501,$B$5,Cleaned_Data!$L$2:$L$501,$B$6) -> 47 | E21: =IF($B$35=0,0,B21/$B$35) -> 0.15014986 | F21: =SUMIFS(Cleaned_Data!$G$2:$G$501,Cleaned_Data!$C$2:$C$501,$A21) -> 234953
A22: Running Shoes | B22: =SUMIFS(Cleaned_Data!$G$2:$G$501,Cleaned_Data!$C$2:$C$501,$A22,Cleaned_Data!$D$2:$D$501,$B$3,Cleaned_Data!$I$2:$I$501,$B$4,Cleaned_Data!$N$2:$N$501,$B$5,Cleaned_Data!$L$2:$L$501,$B$6) -> 214435 | C22: =COUNTIFS(Cleaned_Data!$C$2:$C$501,$A22,Cleaned_Data!$D$2:$D$501,$B$3,Cleaned_Data!$I$2:$I$501,$B$4,Cleaned_Data!$N$2:$N$501,$B$5,Cleaned_Data!$L$2:$L$501,$B$6) -> 36 | D22: =SUMIFS(Cleaned_Data!$F$2:$F$501,Cleaned_Data!$C$2:$C$501,$A22,Cleaned_Data!$D$2:$D$501,$B$3,Cleaned_Data!$I$2:$I$501,$B$4,Cleaned_Data!$N$2:$N$501,$B$5,Cleaned_Data!$L$2:$L$501,$B$6) -> 65 | E22: =IF($B$35=0,0,B22/$B$35) -> 0.13703756 | F22: =SUMIFS(Cleaned_Data!$G$2:$G$501,Cleaned_Data!$C$2:$C$501,$A22) -> 214435
A23: Mixer Grinder | B23: =SUMIFS(Cleaned_Data!$G$2:$G$501,Cleaned_Data!$C$2:$C$501,$A23,Cleaned_Data!$D$2:$D$501,$B$3,Cleaned_Data!$I$2:$I$501,$B$4,Cleaned_Data!$N$2:$N$501,$B$5,Cleaned_Data!$L$2:$L$501,$B$6) -> 188946 | C23: =COUNTIFS(Cleaned_Data!$C$2:$C$501,$A23,Cleaned_Data!$D$2:$D$501,$B$3,Cleaned_Data!$I$2:$I$501,$B$4,Cleaned_Data!$N$2:$N$501,$B$5,Cleaned_Data!$L$2:$L$501,$B$6) -> 29 | D23: =SUMIFS(Cleaned_Data!$F$2:$F$501,Cleaned_Data!$C$2:$C$501,$A23,Cleaned_Data!$D$2:$D$501,$B$3,Cleaned_Data!$I$2:$I$501,$B$4,Cleaned_Data!$N$2:$N$501,$B$5,Cleaned_Data!$L$2:$L$501,$B$6) -> 54 | E23: =IF($B$35=0,0,B23/$B$35) -> 0.12074847 | F23: =SUMIFS(Cleaned_Data!$G$2:$G$501,Cleaned_Data!$C$2:$C$501,$A23) -> 188946
A24: Wireless Earbuds | B24: =SUMIFS(Cleaned_Data!$G$2:$G$501,Cleaned_Data!$C$2:$C$501,$A24,Cleaned_Data!$D$2:$D$501,$B$3,Cleaned_Data!$I$2:$I$501,$B$4,Cleaned_Data!$N$2:$N$501,$B$5,Cleaned_Data!$L$2:$L$501,$B$6) -> 184926 | C24: =COUNTIFS(Cleaned_Data!$C$2:$C$501,$A24,Cleaned_Data!$D$2:$D$501,$B$3,Cleaned_Data!$I$2:$I$501,$B$4,Cleaned_Data!$N$2:$N$501,$B$5,Cleaned_Data!$L$2:$L$501,$B$6) -> 46 | D24: =SUMIFS(Cleaned_Data!$F$2:$F$501,Cleaned_Data!$C$2:$C$501,$A24,Cleaned_Data!$D$2:$D$501,$B$3,Cleaned_Data!$I$2:$I$501,$B$4,Cleaned_Data!$N$2:$N$501,$B$5,Cleaned_Data!$L$2:$L$501,$B$6) -> 74 | E24: =IF($B$35=0,0,B24/$B$35) -> 0.11817944 | F24: =SUMIFS(Cleaned_Data!$G$2:$G$501,Cleaned_Data!$C$2:$C$501,$A24) -> 184926
A25: Air Fryer | B25: =SUMIFS(Cleaned_Data!$G$2:$G$501,Cleaned_Data!$C$2:$C$501,$A25,Cleaned_Data!$D$2:$D$501,$B$3,Cleaned_Data!$I$2:$I$501,$B$4,Cleaned_Data!$N$2:$N$501,$B$5,Cleaned_Data!$L$2:$L$501,$B$6) -> 173971 | C25: =COUNTIFS(Cleaned_Data!$C$2:$C$501,$A25,Cleaned_Data!$D$2:$D$501,$B$3,Cleaned_Data!$I$2:$I$501,$B$4,Cleaned_Data!$N$2:$N$501,$B$5,Cleaned_Data!$L$2:$L$501,$B$6) -> 18 | D25: =SUMIFS(Cleaned_Data!$F$2:$F$501,Cleaned_Data!$C$2:$C$501,$A25,Cleaned_Data!$D$2:$D$501,$B$3,Cleaned_Data!$I$2:$I$501,$B$4,Cleaned_Data!$N$2:$N$501,$B$5,Cleaned_Data!$L$2:$L$501,$B$6) -> 29 | E25: =IF($B$35=0,0,B25/$B$35) -> 0.1111785 | F25: =SUMIFS(Cleaned_Data!$G$2:$G$501,Cleaned_Data!$C$2:$C$501,$A25) -> 173971
A26: Casual Sneakers | B26: =SUMIFS(Cleaned_Data!$G$2:$G$501,Cleaned_Data!$C$2:$C$501,$A26,Cleaned_Data!$D$2:$D$501,$B$3,Cleaned_Data!$I$2:$I$501,$B$4,Cleaned_Data!$N$2:$N$501,$B$5,Cleaned_Data!$L$2:$L$501,$B$6) -> 101154 | C26: =COUNTIFS(Cleaned_Data!$C$2:$C$501,$A26,Cleaned_Data!$D$2:$D$501,$B$3,Cleaned_Data!$I$2:$I$501,$B$4,Cleaned_Data!$N$2:$N$501,$B$5,Cleaned_Data!$L$2:$L$501,$B$6) -> 36 | D26: =SUMIFS(Cleaned_Data!$F$2:$F$501,Cleaned_Data!$C$2:$C$501,$A26,Cleaned_Data!$D$2:$D$501,$B$3,Cleaned_Data!$I$2:$I$501,$B$4,Cleaned_Data!$N$2:$N$501,$B$5,Cleaned_Data!$L$2:$L$501,$B$6) -> 46 | E26: =IF($B$35=0,0,B26/$B$35) -> 0.064643818 | F26: =SUMIFS(Cleaned_Data!$G$2:$G$501,Cleaned_Data!$C$2:$C$501,$A26) -> 101154
A27: Denim Jeans | B27: =SUMIFS(Cleaned_Data!$G$2:$G$501,Cleaned_Data!$C$2:$C$501,$A27,Cleaned_Data!$D$2:$D$501,$B$3,Cleaned_Data!$I$2:$I$501,$B$4,Cleaned_Data!$N$2:$N$501,$B$5,Cleaned_Data!$L$2:$L$501,$B$6) -> 98945 | C27: =COUNTIFS(Cleaned_Data!$C$2:$C$501,$A27,Cleaned_Data!$D$2:$D$501,$B$3,Cleaned_Data!$I$2:$I$501,$B$4,Cleaned_Data!$N$2:$N$501,$B$5,Cleaned_Data!$L$2:$L$501,$B$6) -> 33 | D27: =SUMIFS(Cleaned_Data!$F$2:$F$501,Cleaned_Data!$C$2:$C$501,$A27,Cleaned_Data!$D$2:$D$501,$B$3,Cleaned_Data!$I$2:$I$501,$B$4,Cleaned_Data!$N$2:$N$501,$B$5,Cleaned_Data!$L$2:$L$501,$B$6) -> 55 | E27: =IF($B$35=0,0,B27/$B$35) -> 0.063232127 | F27: =SUMIFS(Cleaned_Data!$G$2:$G$501,Cleaned_Data!$C$2:$C$501,$A27) -> 98945
A28: Bluetooth Speaker | B28: =SUMIFS(Cleaned_Data!$G$2:$G$501,Cleaned_Data!$C$2:$C$501,$A28,Cleaned_Data!$D$2:$D$501,$B$3,Cleaned_Data!$I$2:$I$501,$B$4,Cleaned_Data!$N$2:$N$501,$B$5,Cleaned_Data!$L$2:$L$501,$B$6) -> 95952 | C28: =COUNTIFS(Cleaned_Data!$C$2:$C$501,$A28,Cleaned_Data!$D$2:$D$501,$B$3,Cleaned_Data!$I$2:$I$501,$B$4,Cleaned_Data!$N$2:$N$501,$B$5,Cleaned_Data!$L$2:$L$501,$B$6) -> 30 | D28: =SUMIFS(Cleaned_Data!$F$2:$F$501,Cleaned_Data!$C$2:$C$501,$A28,Cleaned_Data!$D$2:$D$501,$B$3,Cleaned_Data!$I$2:$I$501,$B$4,Cleaned_Data!$N$2:$N$501,$B$5,Cleaned_Data!$L$2:$L$501,$B$6) -> 48 | E28: =IF($B$35=0,0,B28/$B$35) -> 0.06131941 | F28: =SUMIFS(Cleaned_Data!$G$2:$G$501,Cleaned_Data!$C$2:$C$501,$A28) -> 95952
A29: Power Bank | B29: =SUMIFS(Cleaned_Data!$G$2:$G$501,Cleaned_Data!$C$2:$C$501,$A29,Cleaned_Data!$D$2:$D$501,$B$3,Cleaned_Data!$I$2:$I$501,$B$4,Cleaned_Data!$N$2:$N$501,$B$5,Cleaned_Data!$L$2:$L$501,$B$6) -> 79239 | C29: =COUNTIFS(Cleaned_Data!$C$2:$C$501,$A29,Cleaned_Data!$D$2:$D$501,$B$3,Cleaned_Data!$I$2:$I$501,$B$4,Cleaned_Data!$N$2:$N$501,$B$5,Cleaned_Data!$L$2:$L$501,$B$6) -> 39 | D29: =SUMIFS(Cleaned_Data!$F$2:$F$501,Cleaned_Data!$C$2:$C$501,$A29,Cleaned_Data!$D$2:$D$501,$B$3,Cleaned_Data!$I$2:$I$501,$B$4,Cleaned_Data!$N$2:$N$501,$B$5,Cleaned_Data!$L$2:$L$501,$B$6) -> 61 | E29: =IF($B$35=0,0,B29/$B$35) -> 0.050638744 | F29: =SUMIFS(Cleaned_Data!$G$2:$G$501,Cleaned_Data!$C$2:$C$501,$A29) -> 79239
A30: Water Bottle | B30: =SUMIFS(Cleaned_Data!$G$2:$G$501,Cleaned_Data!$C$2:$C$501,$A30,Cleaned_Data!$D$2:$D$501,$B$3,Cleaned_Data!$I$2:$I$501,$B$4,Cleaned_Data!$N$2:$N$501,$B$5,Cleaned_Data!$L$2:$L$501,$B$6) -> 53393 | C30: =COUNTIFS(Cleaned_Data!$C$2:$C$501,$A30,Cleaned_Data!$D$2:$D$501,$B$3,Cleaned_Data!$I$2:$I$501,$B$4,Cleaned_Data!$N$2:$N$501,$B$5,Cleaned_Data!$L$2:$L$501,$B$6) -> 66 | D30: =SUMIFS(Cleaned_Data!$F$2:$F$501,Cleaned_Data!$C$2:$C$501,$A30,Cleaned_Data!$D$2:$D$501,$B$3,Cleaned_Data!$I$2:$I$501,$B$4,Cleaned_Data!$N$2:$N$501,$B$5,Cleaned_Data!$L$2:$L$501,$B$6) -> 107 | E30: =IF($B$35=0,0,B30/$B$35) -> 0.034121512 | F30: =SUMIFS(Cleaned_Data!$G$2:$G$501,Cleaned_Data!$C$2:$C$501,$A30) -> 53393
A31: Sandals | B31: =SUMIFS(Cleaned_Data!$G$2:$G$501,Cleaned_Data!$C$2:$C$501,$A31,Cleaned_Data!$D$2:$D$501,$B$3,Cleaned_Data!$I$2:$I$501,$B$4,Cleaned_Data!$N$2:$N$501,$B$5,Cleaned_Data!$L$2:$L$501,$B$6) -> 41354 | C31: =COUNTIFS(Cleaned_Data!$C$2:$C$501,$A31,Cleaned_Data!$D$2:$D$501,$B$3,Cleaned_Data!$I$2:$I$501,$B$4,Cleaned_Data!$N$2:$N$501,$B$5,Cleaned_Data!$L$2:$L$501,$B$6) -> 25 | D31: =SUMIFS(Cleaned_Data!$F$2:$F$501,Cleaned_Data!$C$2:$C$501,$A31,Cleaned_Data!$D$2:$D$501,$B$3,Cleaned_Data!$I$2:$I$501,$B$4,Cleaned_Data!$N$2:$N$501,$B$5,Cleaned_Data!$L$2:$L$501,$B$6) -> 46 | E31: =IF($B$35=0,0,B31/$B$35) -> 0.026427827 | F31: =SUMIFS(Cleaned_Data!$G$2:$G$501,Cleaned_Data!$C$2:$C$501,$A31) -> 41354
A32: Cotton T-Shirt | B32: =SUMIFS(Cleaned_Data!$G$2:$G$501,Cleaned_Data!$C$2:$C$501,$A32,Cleaned_Data!$D$2:$D$501,$B$3,Cleaned_Data!$I$2:$I$501,$B$4,Cleaned_Data!$N$2:$N$501,$B$5,Cleaned_Data!$L$2:$L$501,$B$6) -> 37138 | C32: =COUNTIFS(Cleaned_Data!$C$2:$C$501,$A32,Cleaned_Data!$D$2:$D$501,$B$3,Cleaned_Data!$I$2:$I$501,$B$4,Cleaned_Data!$N$2:$N$501,$B$5,Cleaned_Data!$L$2:$L$501,$B$6) -> 37 | D32: =SUMIFS(Cleaned_Data!$F$2:$F$501,Cleaned_Data!$C$2:$C$501,$A32,Cleaned_Data!$D$2:$D$501,$B$3,Cleaned_Data!$I$2:$I$501,$B$4,Cleaned_Data!$N$2:$N$501,$B$5,Cleaned_Data!$L$2:$L$501,$B$6) -> 62 | E32: =IF($B$35=0,0,B32/$B$35) -> 0.023733536 | F32: =SUMIFS(Cleaned_Data!$G$2:$G$501,Cleaned_Data!$C$2:$C$501,$A32) -> 37138
... A34: Self Help Book | B34: =SUMIFS(Cleaned_Data!$G$2:$G$501,Cleaned_Data!$C$2:$C$501,$A34,Cleaned_Data!$D$2:$D$501,$B$3,Cleaned_Data!$I$2:$I$501,$B$4,Cleaned_Data!$N$2:$N$501,$B$5,Cleaned_Data!$L$2:$L$501,$B$6) -> 27531 | C34: =COUNTIFS(Cleaned_Data!$C$2:$C$501,$A34,Cleaned_Data!$D$2:$D$501,$B$3,Cleaned_Data!$I$2:$I$501,$B$4,Cleaned_Data!$N$2:$N$501,$B$5,Cleaned_Data!$L$2:$L$501,$B$6) -> 42 | D34: =SUMIFS(Cleaned_Data!$F$2:$F$501,Cleaned_Data!$C$2:$C$501,$A34,Cleaned_Data!$D$2:$D$501,$B$3,Cleaned_Data!$I$2:$I$501,$B$4,Cleaned_Data!$N$2:$N$501,$B$5,Cleaned_Data!$L$2:$L$501,$B$6) -> 69 | E34: =IF($B$35=0,0,B34/$B$35) -> 0.017594054 | F34: =SUMIFS(Cleaned_Data!$G$2:$G$501,Cleaned_Data!$C$2:$C$501,$A34) -> 27531
A35: Grand Total | B35: =SUM(B21:B34) -> 1564790 | C35: =SUM(C21:C34) -> 500 | D35: =SUM(D21:D34) -> 810 | E35: =SUM(E21:E34) -> 1 | F35: =SUM(F21:F34) -> 1564790
A38: City-wise Total Sales
A39: Item | B39: Total Sales | C39: Orders | D39: Units Sold | E39: % of Sales | F39: Total Sales (all data)
A40: Mumbai | B40: =SUMIFS(Cleaned_Data!$G$2:$G$501,Cleaned_Data!$I$2:$I$501,$A40,Cleaned_Data!$D$2:$D$501,$B$3,Cleaned_Data!$N$2:$N$501,$B$5,Cleaned_Data!$L$2:$L$501,$B$6) -> 351454 | C40: =COUNTIFS(Cleaned_Data!$I$2:$I$501,$A40,Cleaned_Data!$D$2:$D$501,$B$3,Cleaned_Data!$N$2:$N$501,$B$5,Cleaned_Data!$L$2:$L$501,$B$6) -> 85 | D40: =SUMIFS(Cleaned_Data!$F$2:$F$501,Cleaned_Data!$I$2:$I$501,$A40,Cleaned_Data!$D$2:$D$501,$B$3,Cleaned_Data!$N$2:$N$501,$B$5,Cleaned_Data!$L$2:$L$501,$B$6) -> 146 | E40: =IF($B$50=0,0,B40/$B$50) -> 0.22460138 | F40: =SUMIFS(Cleaned_Data!$G$2:$G$501,Cleaned_Data!$I$2:$I$501,$A40) -> 351454
A41: Bangalore | B41: =SUMIFS(Cleaned_Data!$G$2:$G$501,Cleaned_Data!$I$2:$I$501,$A41,Cleaned_Data!$D$2:$D$501,$B$3,Cleaned_Data!$N$2:$N$501,$B$5,Cleaned_Data!$L$2:$L$501,$B$6) -> 296448 | C41: =COUNTIFS(Cleaned_Data!$I$2:$I$501,$A41,Cleaned_Data!$D$2:$D$501,$B$3,Cleaned_Data!$N$2:$N$501,$B$5,Cleaned_Data!$L$2:$L$501,$B$6) -> 97 | D41: =SUMIFS(Cleaned_Data!$F$2:$F$501,Cleaned_Data!$I$2:$I$501,$A41,Cleaned_Data!$D$2:$D$501,$B$3,Cleaned_Data!$N$2:$N$501,$B$5,Cleaned_Data!$L$2:$L$501,$B$6) -> 152 | E41: =IF($B$50=0,0,B41/$B$50) -> 0.18944906 | F41: =SUMIFS(Cleaned_Data!$G$2:$G$501,Cleaned_Data!$I$2:$I$501,$A41) -> 296448
A42: Hyderabad | B42: =SUMIFS(Cleaned_Data!$G$2:$G$501,Cleaned_Data!$I$2:$I$501,$A42,Cleaned_Data!$D$2:$D$501,$B$3,Cleaned_Data!$N$2:$N$501,$B$5,Cleaned_Data!$L$2:$L$501,$B$6) -> 236367 | C42: =COUNTIFS(Cleaned_Data!$I$2:$I$501,$A42,Cleaned_Data!$D$2:$D$501,$B$3,Cleaned_Data!$N$2:$N$501,$B$5,Cleaned_Data!$L$2:$L$501,$B$6) -> 83 | D42: =SUMIFS(Cleaned_Data!$F$2:$F$501,Cleaned_Data!$I$2:$I$501,$A42,Cleaned_Data!$D$2:$D$501,$B$3,Cleaned_Data!$N$2:$N$501,$B$5,Cleaned_Data!$L$2:$L$501,$B$6) -> 133 | E42: =IF($B$50=0,0,B42/$B$50) -> 0.1510535 | F42: =SUMIFS(Cleaned_Data!$G$2:$G$501,Cleaned_Data!$I$2:$I$501,$A42) -> 236367
A43: Delhi | B43: =SUMIFS(Cleaned_Data!$G$2:$G$501,Cleaned_Data!$I$2:$I$501,$A43,Cleaned_Data!$D$2:$D$501,$B$3,Cleaned_Data!$N$2:$N$501,$B$5,Cleaned_Data!$L$2:$L$501,$B$6) -> 206192 | C43: =COUNTIFS(Cleaned_Data!$I$2:$I$501,$A43,Cleaned_Data!$D$2:$D$501,$B$3,Cleaned_Data!$N$2:$N$501,$B$5,Cleaned_Data!$L$2:$L$501,$B$6) -> 69 | D43: =SUMIFS(Cleaned_Data!$F$2:$F$501,Cleaned_Data!$I$2:$I$501,$A43,Cleaned_Data!$D$2:$D$501,$B$3,Cleaned_Data!$N$2:$N$501,$B$5,Cleaned_Data!$L$2:$L$501,$B$6) -> 108 | E43: =IF($B$50=0,0,B43/$B$50) -> 0.13176976 | F43: =SUMIFS(Cleaned_Data!$G$2:$G$501,Cleaned_Data!$I$2:$I$501,$A43) -> 206192
A44: Pune | B44: =SUMIFS(Cleaned_Data!$G$2:$G$501,Cleaned_Data!$I$2:$I$501,$A44,Cleaned_Data!$D$2:$D$501,$B$3,Cleaned_Data!$N$2:$N$501,$B$5,Cleaned_Data!$L$2:$L$501,$B$6) -> 135923 | C44: =COUNTIFS(Cleaned_Data!$I$2:$I$501,$A44,Cleaned_Data!$D$2:$D$501,$B$3,Cleaned_Data!$N$2:$N$501,$B$5,Cleaned_Data!$L$2:$L$501,$B$6) -> 50 | D44: =SUMIFS(Cleaned_Data!$F$2:$F$501,Cleaned_Data!$I$2:$I$501,$A44,Cleaned_Data!$D$2:$D$501,$B$3,Cleaned_Data!$N$2:$N$501,$B$5,Cleaned_Data!$L$2:$L$501,$B$6) -> 77 | E44: =IF($B$50=0,0,B44/$B$50) -> 0.086863413 | F44: =SUMIFS(Cleaned_Data!$G$2:$G$501,Cleaned_Data!$I$2:$I$501,$A44) -> 135923
A45: Kolkata | B45: =SUMIFS(Cleaned_Data!$G$2:$G$501,Cleaned_Data!$I$2:$I$501,$A45,Cleaned_Data!$D$2:$D$501,$B$3,Cleaned_Data!$N$2:$N$501,$B$5,Cleaned_Data!$L$2:$L$501,$B$6) -> 90757 | C45: =COUNTIFS(Cleaned_Data!$I$2:$I$501,$A45,Cleaned_Data!$D$2:$D$501,$B$3,Cleaned_Data!$N$2:$N$501,$B$5,Cleaned_Data!$L$2:$L$501,$B$6) -> 29 | D45: =SUMIFS(Cleaned_Data!$F$2:$F$501,Cleaned_Data!$I$2:$I$501,$A45,Cleaned_Data!$D$2:$D$501,$B$3,Cleaned_Data!$N$2:$N$501,$B$5,Cleaned_Data!$L$2:$L$501,$B$6) -> 43 | E45: =IF($B$50=0,0,B45/$B$50) -> 0.057999476 | F45: =SUMIFS(Cleaned_Data!$G$2:$G$501,Cleaned_Data!$I$2:$I$501,$A45) -> 90757
A46: Lucknow | B46: =SUMIFS(Cleaned_Data!$G$2:$G$501,Cleaned_Data!$I$2:$I$501,$A46,Cleaned_Data!$D$2:$D$501,$B$3,Cleaned_Data!$N$2:$N$501,$B$5,Cleaned_Data!$L$2:$L$501,$B$6) -> 79755 | C46: =COUNTIFS(Cleaned_Data!$I$2:$I$501,$A46,Cleaned_Data!$D$2:$D$501,$B$3,Cleaned_Data!$N$2:$N$501,$B$5,Cleaned_Data!$L$2:$L$501,$B$6) -> 27 | D46: =SUMIFS(Cleaned_Data!$F$2:$F$501,Cleaned_Data!$I$2:$I$501,$A46,Cleaned_Data!$D$2:$D$501,$B$3,Cleaned_Data!$N$2:$N$501,$B$5,Cleaned_Data!$L$2:$L$501,$B$6) -> 45 | E46: =IF($B$50=0,0,B46/$B$50) -> 0.050968501 | F46: =SUMIFS(Cleaned_Data!$G$2:$G$501,Cleaned_Data!$I$2:$I$501,$A46) -> 79755
A47: Ahmedabad | B47: =SUMIFS(Cleaned_Data!$G$2:$G$501,Cleaned_Data!$I$2:$I$501,$A47,Cleaned_Data!$D$2:$D$501,$B$3,Cleaned_Data!$N$2:$N$501,$B$5,Cleaned_Data!$L$2:$L$501,$B$6) -> 78747 | C47: =COUNTIFS(Cleaned_Data!$I$2:$I$501,$A47,Cleaned_Data!$D$2:$D$501,$B$3,Cleaned_Data!$N$2:$N$501,$B$5,Cleaned_Data!$L$2:$L$501,$B$6) -> 27 | D47: =SUMIFS(Cleaned_Data!$F$2:$F$501,Cleaned_Data!$I$2:$I$501,$A47,Cleaned_Data!$D$2:$D$501,$B$3,Cleaned_Data!$N$2:$N$501,$B$5,Cleaned_Data!$L$2:$L$501,$B$6) -> 53 | E47: =IF($B$50=0,0,B47/$B$50) -> 0.050324325 | F47: =SUMIFS(Cleaned_Data!$G$2:$G$501,Cleaned_Data!$I$2:$I$501,$A47) -> 78747
A48: Chennai | B48: =SUMIFS(Cleaned_Data!$G$2:$G$501,Cleaned_Data!$I$2:$I$501,$A48,Cleaned_Data!$D$2:$D$501,$B$3,Cleaned_Data!$N$2:$N$501,$B$5,Cleaned_Data!$L$2:$L$501,$B$6) -> 61766 | C48: =COUNTIFS(Cleaned_Data!$I$2:$I$501,$A48,Cleaned_Data!$D$2:$D$501,$B$3,Cleaned_Data!$N$2:$N$501,$B$5,Cleaned_Data!$L$2:$L$501,$B$6) -> 18 | D48: =SUMIFS(Cleaned_Data!$F$2:$F$501,Cleaned_Data!$I$2:$I$501,$A48,Cleaned_Data!$D$2:$D$501,$B$3,Cleaned_Data!$N$2:$N$501,$B$5,Cleaned_Data!$L$2:$L$501,$B$6) -> 34 | E48: =IF($B$50=0,0,B48/$B$50) -> 0.039472389 | F48: =SUMIFS(Cleaned_Data!$G$2:$G$501,Cleaned_Data!$I$2:$I$501,$A48) -> 61766
A49: Jaipur | B49: =SUMIFS(Cleaned_Data!$G$2:$G$501,Cleaned_Data!$I$2:$I$501,$A49,Cleaned_Data!$D$2:$D$501,$B$3,Cleaned_Data!$N$2:$N$501,$B$5,Cleaned_Data!$L$2:$L$501,$B$6) -> 27381 | C49: =COUNTIFS(Cleaned_Data!$I$2:$I$501,$A49,Cleaned_Data!$D$2:$D$501,$B$3,Cleaned_Data!$N$2:$N$501,$B$5,Cleaned_Data!$L$2:$L$501,$B$6) -> 15 | D49: =SUMIFS(Cleaned_Data!$F$2:$F$501,Cleaned_Data!$I$2:$I$501,$A49,Cleaned_Data!$D$2:$D$501,$B$3,Cleaned_Data!$N$2:$N$501,$B$5,Cleaned_Data!$L$2:$L$501,$B$6) -> 19 | E49: =IF($B$50=0,0,B49/$B$50) -> 0.017498195 | F49: =SUMIFS(Cleaned_Data!$G$2:$G$501,Cleaned_Data!$I$2:$I$501,$A49) -> 27381
A50: Grand Total | B50: =SUM(B40:B49) -> 1564790 | C50: =SUM(C40:C49) -> 500 | D50: =SUM(D40:D49) -> 810 | E50: =SUM(E40:E49) -> 1 | F50: =SUM(F40:F49) -> 1564790
A53: Payment Method Usage
A54: Item | B54: Total Sales | C54: Orders | D54: Units Sold | E54: % of Sales | F54: Total Sales (all data)
A55: UPI | B55: =SUMIFS(Cleaned_Data!$G$2:$G$501,Cleaned_Data!$J$2:$J$501,$A55,Cleaned_Data!$D$2:$D$501,$B$3,Cleaned_Data!$I$2:$I$501,$B$4,Cleaned_Data!$N$2:$N$501,$B$5,Cleaned_Data!$L$2:$L$501,$B$6) -> 552508 | C55: =COUNTIFS(Cleaned_Data!$J$2:$J$501,$A55,Cleaned_Data!$D$2:$D$501,$B$3,Cleaned_Data!$I$2:$I$501,$B$4,Cleaned_Data!$N$2:$N$501,$B$5,Cleaned_Data!$L$2:$L$501,$B$6) -> 178 | D55: =SUMIFS(Cleaned_Data!$F$2:$F$501,Cleaned_Data!$J$2:$J$501,$A55,Cleaned_Data!$D$2:$D$501,$B$3,Cleaned_Data!$I$2:$I$501,$B$4,Cleaned_Data!$N$2:$N$501,$B$5,Cleaned_Data!$L$2:$L$501,$B$6) -> 292 | E55: =IF($B$60=0,0,B55/$B$60) -> 0.35308763 | F55: =SUMIFS(Cleaned_Data!$G$2:$G$501,Cleaned_Data!$J$2:$J$501,$A55) -> 552508
A56: Debit Card | B56: =SUMIFS(Cleaned_Data!$G$2:$G$501,Cleaned_Data!$J$2:$J$501,$A56,Cleaned_Data!$D$2:$D$501,$B$3,Cleaned_Data!$I$2:$I$501,$B$4,Cleaned_Data!$N$2:$N$501,$B$5,Cleaned_Data!$L$2:$L$501,$B$6) -> 337642 | C56: =COUNTIFS(Cleaned_Data!$J$2:$J$501,$A56,Cleaned_Data!$D$2:$D$501,$B$3,Cleaned_Data!$I$2:$I$501,$B$4,Cleaned_Data!$N$2:$N$501,$B$5,Cleaned_Data!$L$2:$L$501,$B$6) -> 102 | D56: =SUMIFS(Cleaned_Data!$F$2:$F$501,Cleaned_Data!$J$2:$J$501,$A56,Cleaned_Data!$D$2:$D$501,$B$3,Cleaned_Data!$I$2:$I$501,$B$4,Cleaned_Data!$N$2:$N$501,$B$5,Cleaned_Data!$L$2:$L$501,$B$6) -> 158 | E56: =IF($B$60=0,0,B56/$B$60) -> 0.21577464 | F56: =SUMIFS(Cleaned_Data!$G$2:$G$501,Cleaned_Data!$J$2:$J$501,$A56) -> 337642
A57: Credit Card | B57: =SUMIFS(Cleaned_Data!$G$2:$G$501,Cleaned_Data!$J$2:$J$501,$A57,Cleaned_Data!$D$2:$D$501,$B$3,Cleaned_Data!$I$2:$I$501,$B$4,Cleaned_Data!$N$2:$N$501,$B$5,Cleaned_Data!$L$2:$L$501,$B$6) -> 335010 | C57: =COUNTIFS(Cleaned_Data!$J$2:$J$501,$A57,Cleaned_Data!$D$2:$D$501,$B$3,Cleaned_Data!$I$2:$I$501,$B$4,Cleaned_Data!$N$2:$N$501,$B$5,Cleaned_Data!$L$2:$L$501,$B$6) -> 116 | D57: =SUMIFS(Cleaned_Data!$F$2:$F$501,Cleaned_Data!$J$2:$J$501,$A57,Cleaned_Data!$D$2:$D$501,$B$3,Cleaned_Data!$I$2:$I$501,$B$4,Cleaned_Data!$N$2:$N$501,$B$5,Cleaned_Data!$L$2:$L$501,$B$6) -> 190 | E57: =IF($B$60=0,0,B57/$B$60) -> 0.21409263 | F57: =SUMIFS(Cleaned_Data!$G$2:$G$501,Cleaned_Data!$J$2:$J$501,$A57) -> 335010
A58: Cash On Delivery | B58: =SUMIFS(Cleaned_Data!$G$2:$G$501,Cleaned_Data!$J$2:$J$501,$A58,Cleaned_Data!$D$2:$D$501,$B$3,Cleaned_Data!$I$2:$I$501,$B$4,Cleaned_Data!$N$2:$N$501,$B$5,Cleaned_Data!$L$2:$L$501,$B$6) -> 204795 | C58: =COUNTIFS(Cleaned_Data!$J$2:$J$501,$A58,Cleaned_Data!$D$2:$D$501,$B$3,Cleaned_Data!$I$2:$I$501,$B$4,Cleaned_Data!$N$2:$N$501,$B$5,Cleaned_Data!$L$2:$L$501,$B$6) -> 66 | D58: =SUMIFS(Cleaned_Data!$F$2:$F$501,Cleaned_Data!$J$2:$J$501,$A58,Cleaned_Data!$D$2:$D$501,$B$3,Cleaned_Data!$I$2:$I$501,$B$4,Cleaned_Data!$N$2:$N$501,$B$5,Cleaned_Data!$L$2:$L$501,$B$6) -> 105 | E58: =IF($B$60=0,0,B58/$B$60) -> 0.13087699 | F58: =SUMIFS(Cleaned_Data!$G$2:$G$501,Cleaned_Data!$J$2:$J$501,$A58) -> 204795
A59: Net Banking | B59: =SUMIFS(Cleaned_Data!$G$2:$G$501,Cleaned_Data!$J$2:$J$501,$A59,Cleaned_Data!$D$2:$D$501,$B$3,Cleaned_Data!$I$2:$I$501,$B$4,Cleaned_Data!$N$2:$N$501,$B$5,Cleaned_Data!$L$2:$L$501,$B$6) -> 134835 | C59: =COUNTIFS(Cleaned_Data!$J$2:$J$501,$A59,Cleaned_Data!$D$2:$D$501,$B$3,Cleaned_Data!$I$2:$I$501,$B$4,Cleaned_Data!$N$2:$N$501,$B$5,Cleaned_Data!$L$2:$L$501,$B$6) -> 38 | D59: =SUMIFS(Cleaned_Data!$F$2:$F$501,Cleaned_Data!$J$2:$J$501,$A59,Cleaned_Data!$D$2:$D$501,$B$3,Cleaned_Data!$I$2:$I$501,$B$4,Cleaned_Data!$N$2:$N$501,$B$5,Cleaned_Data!$L$2:$L$501,$B$6) -> 65 | E59: =IF($B$60=0,0,B59/$B$60) -> 0.086168112 | F59: =SUMIFS(Cleaned_Data!$G$2:$G$501,Cleaned_Data!$J$2:$J$501,$A59) -> 134835
A60: Grand Total | B60: =SUM(B55:B59) -> 1564790 | C60: =SUM(C55:C59) -> 500 | D60: =SUM(D55:D59) -> 810 | E60: =SUM(E55:E59) -> 1 | F60: =SUM(F55:F59) -> 1564790
A63: Order Status Distribution (ignores Status filter)
A64: Item | B64: Total Sales | C64: Orders | D64: Units Sold | E64: % of Sales | F64: Total Sales (all data)
A65: Delivered | B65: =SUMIFS(Cleaned_Data!$G$2:$G$501,Cleaned_Data!$N$2:$N$501,$A65,Cleaned_Data!$D$2:$D$501,$B$3,Cleaned_Data!$I$2:$I$501,$B$4,Cleaned_Data!$L$2:$L$501,$B$6) -> 1161876 | C65: =COUNTIFS(Cleaned_Data!$N$2:$N$501,$A65,Cleaned_Data!$D$2:$D$501,$B$3,Cleaned_Data!$I$2:$I$501,$B$4,Cleaned_Data!$L$2:$L$501,$B$6) -> 382 | D65: =SUMIFS(Cleaned_Data!$F$2:$F$501,Cleaned_Data!$N$2:$N$501,$A65,Cleaned_Data!$D$2:$D$501,$B$3,Cleaned_Data!$I$2:$I$501,$B$4,Cleaned_Data!$L$2:$L$501,$B$6) -> 624 | E65: =IF($B$68=0,0,B65/$B$68) -> 0.74251241 | F65: =SUMIFS(Cleaned_Data!$G$2:$G$501,Cleaned_Data!$N$2:$N$501,$A65) -> 1161876
A66: Pending | B66: =SUMIFS(Cleaned_Data!$G$2:$G$501,Cleaned_Data!$N$2:$N$501,$A66,Cleaned_Data!$D$2:$D$501,$B$3,Cleaned_Data!$I$2:$I$501,$B$4,Cleaned_Data!$L$2:$L$501,$B$6) -> 190422 | C66: =COUNTIFS(Cleaned_Data!$N$2:$N$501,$A66,Cleaned_Data!$D$2:$D$501,$B$3,Cleaned_Data!$I$2:$I$501,$B$4,Cleaned_Data!$L$2:$L$501,$B$6) -> 55 | D66: =SUMIFS(Cleaned_Data!$F$2:$F$501,Cleaned_Data!$N$2:$N$501,$A66,Cleaned_Data!$D$2:$D$501,$B$3,Cleaned_Data!$I$2:$I$501,$B$4,Cleaned_Data!$L$2:$L$501,$B$6) -> 78 | E66: =IF($B$68=0,0,B66/$B$68) -> 0.12169173 | F66: =SUMIFS(Cleaned_Data!$G$2:$G$501,Cleaned_Data!$N$2:$N$501,$A66) -> 190422
A67: Cancelled | B67: =SUMIFS(Cleaned_Data!$G$2:$G$501,Cleaned_Data!$N$2:$N$501,$A67,Cleaned_Data!$D$2:$D$501,$B$3,Cleaned_Data!$I$2:$I$501,$B$4,Cleaned_Data!$L$2:$L$501,$B$6) -> 212492 | C67: =COUNTIFS(Cleaned_Data!$N$2:$N$501,$A67,Cleaned_Data!$D$2:$D$501,$B$3,Cleaned_Data!$I$2:$I$501,$B$4,Cleaned_Data!$L$2:$L$501,$B$6) -> 63 | D67: =SUMIFS(Cleaned_Data!$F$2:$F$501,Cleaned_Data!$N$2:$N$501,$A67,Cleaned_Data!$D$2:$D$501,$B$3,Cleaned_Data!$I$2:$I$501,$B$4,Cleaned_Data!$L$2:$L$501,$B$6) -> 108 | E67: =IF($B$68=0,0,B67/$B$68) -> 0.13579586 | F67: =SUMIFS(Cleaned_Data!$G$2:$G$501,Cleaned_Data!$N$2:$N$501,$A67) -> 212492
A68: Grand Total | B68: =SUM(B65:B67) -> 1564790 | C68: =SUM(C65:C67) -> 500 | D68: =SUM(D65:D67) -> 810 | E68: =SUM(E65:E67) -> 1 | F68: =SUM(F65:F67) -> 1564790
A71: All Customers by Total Spending
A72: Item | B72: Total Sales | C72: Orders | D72: Units Sold | E72: % of Sales | F72: Total Sales (all data) | G72: Rank helper
A73: Aarav Das | B73: =SUMIFS(Cleaned_Data!$G$2:$G$501,Cleaned_Data!$H$2:$H$501,$A73,Cleaned_Data!$D$2:$D$501,$B$3,Cleaned_Data!$I$2:$I$501,$B$4,Cleaned_Data!$N$2:$N$501,$B$5,Cleaned_Data!$L$2:$L$501,$B$6) -> 20988 | C73: =COUNTIFS(Cleaned_Data!$H$2:$H$501,$A73,Cleaned_Data!$D$2:$D$501,$B$3,Cleaned_Data!$I$2:$I$501,$B$4,Cleaned_Data!$N$2:$N$501,$B$5,Cleaned_Data!$L$2:$L$501,$B$6) -> 9 | D73: =SUMIFS(Cleaned_Data!$F$2:$F$501,Cleaned_Data!$H$2:$H$501,$A73,Cleaned_Data!$D$2:$D$501,$B$3,Cleaned_Data!$I$2:$I$501,$B$4,Cleaned_Data!$N$2:$N$501,$B$5,Cleaned_Data!$L$2:$L$501,$B$6) -> 12 | E73: =IF($B$133=0,0,B73/$B$133) -> 0.013412662 | F73: =SUMIFS(Cleaned_Data!$G$2:$G$501,Cleaned_Data!$H$2:$H$501,$A73) -> 20988 | G73: =B73+ROW()/1000000 -> 20988
A74: Aarav Joshi | B74: =SUMIFS(Cleaned_Data!$G$2:$G$501,Cleaned_Data!$H$2:$H$501,$A74,Cleaned_Data!$D$2:$D$501,$B$3,Cleaned_Data!$I$2:$I$501,$B$4,Cleaned_Data!$N$2:$N$501,$B$5,Cleaned_Data!$L$2:$L$501,$B$6) -> 25986 | C74: =COUNTIFS(Cleaned_Data!$H$2:$H$501,$A74,Cleaned_Data!$D$2:$D$501,$B$3,Cleaned_Data!$I$2:$I$501,$B$4,Cleaned_Data!$N$2:$N$501,$B$5,Cleaned_Data!$L$2:$L$501,$B$6) -> 9 | D74: =SUMIFS(Cleaned_Data!$F$2:$F$501,Cleaned_Data!$H$2:$H$501,$A74,Cleaned_Data!$D$2:$D$501,$B$3,Cleaned_Data!$I$2:$I$501,$B$4,Cleaned_Data!$N$2:$N$501,$B$5,Cleaned_Data!$L$2:$L$501,$B$6) -> 14 | E74: =IF($B$133=0,0,B74/$B$133) -> 0.016606701 | F74: =SUMIFS(Cleaned_Data!$G$2:$G$501,Cleaned_Data!$H$2:$H$501,$A74) -> 25986 | G74: =B74+ROW()/1000000 -> 25986
A75: Aditya Iyer | B75: =SUMIFS(Cleaned_Data!$G$2:$G$501,Cleaned_Data!$H$2:$H$501,$A75,Cleaned_Data!$D$2:$D$501,$B$3,Cleaned_Data!$I$2:$I$501,$B$4,Cleaned_Data!$N$2:$N$501,$B$5,Cleaned_Data!$L$2:$L$501,$B$6) -> 40576 | C75: =COUNTIFS(Cleaned_Data!$H$2:$H$501,$A75,Cleaned_Data!$D$2:$D$501,$B$3,Cleaned_Data!$I$2:$I$501,$B$4,Cleaned_Data!$N$2:$N$501,$B$5,Cleaned_Data!$L$2:$L$501,$B$6) -> 12 | D75: =SUMIFS(Cleaned_Data!$F$2:$F$501,Cleaned_Data!$H$2:$H$501,$A75,Cleaned_Data!$D$2:$D$501,$B$3,Cleaned_Data!$I$2:$I$501,$B$4,Cleaned_Data!$N$2:$N$501,$B$5,Cleaned_Data!$L$2:$L$501,$B$6) -> 24 | E75: =IF($B$133=0,0,B75/$B$133) -> 0.025930636 | F75: =SUMIFS(Cleaned_Data!$G$2:$G$501,Cleaned_Data!$H$2:$H$501,$A75) -> 40576 | G75: =B75+ROW()/1000000 -> 40576
A76: Aditya Kulkarni | B76: =SUMIFS(Cleaned_Data!$G$2:$G$501,Cleaned_Data!$H$2:$H$501,$A76,Cleaned_Data!$D$2:$D$501,$B$3,Cleaned_Data!$I$2:$I$501,$B$4,Cleaned_Data!$N$2:$N$501,$B$5,Cleaned_Data!$L$2:$L$501,$B$6) -> 35086 | C76: =COUNTIFS(Cleaned_Data!$H$2:$H$501,$A76,Cleaned_Data!$D$2:$D$501,$B$3,Cleaned_Data!$I$2:$I$501,$B$4,Cleaned_Data!$N$2:$N$501,$B$5,Cleaned_Data!$L$2:$L$501,$B$6) -> 8 | D76: =SUMIFS(Cleaned_Data!$F$2:$F$501,Cleaned_Data!$H$2:$H$501,$A76,Cleaned_Data!$D$2:$D$501,$B$3,Cleaned_Data!$I$2:$I$501,$B$4,Cleaned_Data!$N$2:$N$501,$B$5,Cleaned_Data!$L$2:$L$501,$B$6) -> 14 | E76: =IF($B$133=0,0,B76/$B$133) -> 0.022422178 | F76: =SUMIFS(Cleaned_Data!$G$2:$G$501,Cleaned_Data!$H$2:$H$501,$A76) -> 35086 | G76: =B76+ROW()/1000000 -> 35086
A77: Aditya Rao | B77: =SUMIFS(Cleaned_Data!$G$2:$G$501,Cleaned_Data!$H$2:$H$501,$A77,Cleaned_Data!$D$2:$D$501,$B$3,Cleaned_Data!$I$2:$I$501,$B$4,Cleaned_Data!$N$2:$N$501,$B$5,Cleaned_Data!$L$2:$L$501,$B$6) -> 17083 | C77: =COUNTIFS(Cleaned_Data!$H$2:$H$501,$A77,Cleaned_Data!$D$2:$D$501,$B$3,Cleaned_Data!$I$2:$I$501,$B$4,Cleaned_Data!$N$2:$N$501,$B$5,Cleaned_Data!$L$2:$L$501,$B$6) -> 8 | D77: =SUMIFS(Cleaned_Data!$F$2:$F$501,Cleaned_Data!$H$2:$H$501,$A77,Cleaned_Data!$D$2:$D$501,$B$3,Cleaned_Data!$I$2:$I$501,$B$4,Cleaned_Data!$N$2:$N$501,$B$5,Cleaned_Data!$L$2:$L$501,$B$6) -> 17 | E77: =IF($B$133=0,0,B77/$B$133) -> 0.01091712 | F77: =SUMIFS(Cleaned_Data!$G$2:$G$501,Cleaned_Data!$H$2:$H$501,$A77) -> 17083 | G77: =B77+ROW()/1000000 -> 17083
A78: Aditya Sharma | B78: =SUMIFS(Cleaned_Data!$G$2:$G$501,Cleaned_Data!$H$2:$H$501,$A78,Cleaned_Data!$D$2:$D$501,$B$3,Cleaned_Data!$I$2:$I$501,$B$4,Cleaned_Data!$N$2:$N$501,$B$5,Cleaned_Data!$L$2:$L$501,$B$6) -> 30478 | C78: =COUNTIFS(Cleaned_Data!$H$2:$H$501,$A78,Cleaned_Data!$D$2:$D$501,$B$3,Cleaned_Data!$I$2:$I$501,$B$4,Cleaned_Data!$N$2:$N$501,$B$5,Cleaned_Data!$L$2:$L$501,$B$6) -> 11 | D78: =SUMIFS(Cleaned_Data!$F$2:$F$501,Cleaned_Data!$H$2:$H$501,$A78,Cleaned_Data!$D$2:$D$501,$B$3,Cleaned_Data!$I$2:$I$501,$B$4,Cleaned_Data!$N$2:$N$501,$B$5,Cleaned_Data!$L$2:$L$501,$B$6) -> 22 | E78: =IF($B$133=0,0,B78/$B$133) -> 0.019477374 | F78: =SUMIFS(Cleaned_Data!$G$2:$G$501,Cleaned_Data!$H$2:$H$501,$A78) -> 30478 | G78: =B78+ROW()/1000000 -> 30478
A79: Aditya Singh | B79: =SUMIFS(Cleaned_Data!$G$2:$G$501,Cleaned_Data!$H$2:$H$501,$A79,Cleaned_Data!$D$2:$D$501,$B$3,Cleaned_Data!$I$2:$I$501,$B$4,Cleaned_Data!$N$2:$N$501,$B$5,Cleaned_Data!$L$2:$L$501,$B$6) -> 27389 | C79: =COUNTIFS(Cleaned_Data!$H$2:$H$501,$A79,Cleaned_Data!$D$2:$D$501,$B$3,Cleaned_Data!$I$2:$I$501,$B$4,Cleaned_Data!$N$2:$N$501,$B$5,Cleaned_Data!$L$2:$L$501,$B$6) -> 9 | D79: =SUMIFS(Cleaned_Data!$F$2:$F$501,Cleaned_Data!$H$2:$H$501,$A79,Cleaned_Data!$D$2:$D$501,$B$3,Cleaned_Data!$I$2:$I$501,$B$4,Cleaned_Data!$N$2:$N$501,$B$5,Cleaned_Data!$L$2:$L$501,$B$6) -> 11 | E79: =IF($B$133=0,0,B79/$B$133) -> 0.017503307 | F79: =SUMIFS(Cleaned_Data!$G$2:$G$501,Cleaned_Data!$H$2:$H$501,$A79) -> 27389 | G79: =B79+ROW()/1000000 -> 27389
A80: Anjali Mehta | B80: =SUMIFS(Cleaned_Data!$G$2:$G$501,Cleaned_Data!$H$2:$H$501,$A80,Cleaned_Data!$D$2:$D$501,$B$3,Cleaned_Data!$I$2:$I$501,$B$4,Cleaned_Data!$N$2:$N$501,$B$5,Cleaned_Data!$L$2:$L$501,$B$6) -> 23585 | C80: =COUNTIFS(Cleaned_Data!$H$2:$H$501,$A80,Cleaned_Data!$D$2:$D$501,$B$3,Cleaned_Data!$I$2:$I$501,$B$4,Cleaned_Data!$N$2:$N$501,$B$5,Cleaned_Data!$L$2:$L$501,$B$6) -> 9 | D80: =SUMIFS(Cleaned_Data!$F$2:$F$501,Cleaned_Data!$H$2:$H$501,$A80,Cleaned_Data!$D$2:$D$501,$B$3,Cleaned_Data!$I$2:$I$501,$B$4,Cleaned_Data!$N$2:$N$501,$B$5,Cleaned_Data!$L$2:$L$501,$B$6) -> 15 | E80: =IF($B$133=0,0,B80/$B$133) -> 0.01507231 | F80: =SUMIFS(Cleaned_Data!$G$2:$G$501,Cleaned_Data!$H$2:$H$501,$A80) -> 23585 | G80: =B80+ROW()/1000000 -> 23585
A81: Anjali Verma | B81: =SUMIFS(Cleaned_Data!$G$2:$G$501,Cleaned_Data!$H$2:$H$501,$A81,Cleaned_Data!$D$2:$D$501,$B$3,Cleaned_Data!$I$2:$I$501,$B$4,Cleaned_Data!$N$2:$N$501,$B$5,Cleaned_Data!$L$2:$L$501,$B$6) -> 59983 | C81: =COUNTIFS(Cleaned_Data!$H$2:$H$501,$A81,Cleaned_Data!$D$2:$D$501,$B$3,Cleaned_Data!$I$2:$I$501,$B$4,Cleaned_Data!$N$2:$N$501,$B$5,Cleaned_Data!$L$2:$L$501,$B$6) -> 9 | D81: =SUMIFS(Cleaned_Data!$F$2:$F$501,Cleaned_Data!$H$2:$H$501,$A81,Cleaned_Data!$D$2:$D$501,$B$3,Cleaned_Data!$I$2:$I$501,$B$4,Cleaned_Data!$N$2:$N$501,$B$5,Cleaned_Data!$L$2:$L$501,$B$6) -> 17 | E81: =IF($B$133=0,0,B81/$B$133) -> 0.038332939 | F81: =SUMIFS(Cleaned_Data!$G$2:$G$501,Cleaned_Data!$H$2:$H$501,$A81) -> 59983 | G81: =B81+ROW()/1000000 -> 59983
A82: Arjun Chopra | B82: =SUMIFS(Cleaned_Data!$G$2:$G$501,Cleaned_Data!$H$2:$H$501,$A82,Cleaned_Data!$D$2:$D$501,$B$3,Cleaned_Data!$I$2:$I$501,$B$4,Cleaned_Data!$N$2:$N$501,$B$5,Cleaned_Data!$L$2:$L$501,$B$6) -> 33487 | C82: =COUNTIFS(Cleaned_Data!$H$2:$H$501,$A82,Cleaned_Data!$D$2:$D$501,$B$3,Cleaned_Data!$I$2:$I$501,$B$4,Cleaned_Data!$N$2:$N$501,$B$5,Cleaned_Data!$L$2:$L$501,$B$6) -> 8 | D82: =SUMIFS(Cleaned_Data!$F$2:$F$501,Cleaned_Data!$H$2:$H$501,$A82,Cleaned_Data!$D$2:$D$501,$B$3,Cleaned_Data!$I$2:$I$501,$B$4,Cleaned_Data!$N$2:$N$501,$B$5,Cleaned_Data!$L$2:$L$501,$B$6) -> 13 | E82: =IF($B$133=0,0,B82/$B$133) -> 0.021400316 | F82: =SUMIFS(Cleaned_Data!$G$2:$G$501,Cleaned_Data!$H$2:$H$501,$A82) -> 33487 | G82: =B82+ROW()/1000000 -> 33487
A83: Arjun Das | B83: =SUMIFS(Cleaned_Data!$G$2:$G$501,Cleaned_Data!$H$2:$H$501,$A83,Cleaned_Data!$D$2:$D$501,$B$3,Cleaned_Data!$I$2:$I$501,$B$4,Cleaned_Data!$N$2:$N$501,$B$5,Cleaned_Data!$L$2:$L$501,$B$6) -> 29191 | C83: =COUNTIFS(Cleaned_Data!$H$2:$H$501,$A83,Cleaned_Data!$D$2:$D$501,$B$3,Cleaned_Data!$I$2:$I$501,$B$4,Cleaned_Data!$N$2:$N$501,$B$5,Cleaned_Data!$L$2:$L$501,$B$6) -> 5 | D83: =SUMIFS(Cleaned_Data!$F$2:$F$501,Cleaned_Data!$H$2:$H$501,$A83,Cleaned_Data!$D$2:$D$501,$B$3,Cleaned_Data!$I$2:$I$501,$B$4,Cleaned_Data!$N$2:$N$501,$B$5,Cleaned_Data!$L$2:$L$501,$B$6) -> 9 | E83: =IF($B$133=0,0,B83/$B$133) -> 0.018654899 | F83: =SUMIFS(Cleaned_Data!$G$2:$G$501,Cleaned_Data!$H$2:$H$501,$A83) -> 29191 | G83: =B83+ROW()/1000000 -> 29191
A84: Arjun Joshi | B84: =SUMIFS(Cleaned_Data!$G$2:$G$501,Cleaned_Data!$H$2:$H$501,$A84,Cleaned_Data!$D$2:$D$501,$B$3,Cleaned_Data!$I$2:$I$501,$B$4,Cleaned_Data!$N$2:$N$501,$B$5,Cleaned_Data!$L$2:$L$501,$B$6) -> 25186 | C84: =COUNTIFS(Cleaned_Data!$H$2:$H$501,$A84,Cleaned_Data!$D$2:$D$501,$B$3,Cleaned_Data!$I$2:$I$501,$B$4,Cleaned_Data!$N$2:$N$501,$B$5,Cleaned_Data!$L$2:$L$501,$B$6) -> 8 | D84: =SUMIFS(Cleaned_Data!$F$2:$F$501,Cleaned_Data!$H$2:$H$501,$A84,Cleaned_Data!$D$2:$D$501,$B$3,Cleaned_Data!$I$2:$I$501,$B$4,Cleaned_Data!$N$2:$N$501,$B$5,Cleaned_Data!$L$2:$L$501,$B$6) -> 14 | E84: =IF($B$133=0,0,B84/$B$133) -> 0.016095451 | F84: =SUMIFS(Cleaned_Data!$G$2:$G$501,Cleaned_Data!$H$2:$H$501,$A84) -> 25186 | G84: =B84+ROW()/1000000 -> 25186
... A132: Vivaan Sharma | B132: =SUMIFS(Cleaned_Data!$G$2:$G$501,Cleaned_Data!$H$2:$H$501,$A132,Cleaned_Data!$D$2:$D$501,$B$3,Cleaned_Data!$I$2:$I$501,$B$4,Cleaned_Data!$N$2:$N$501,$B$5,Cleaned_Data!$L$2:$L$501,$B$6) -> 19887 | C132: =COUNTIFS(Cleaned_Data!$H$2:$H$501,$A132,Cleaned_Data!$D$2:$D$501,$B$3,Cleaned_Data!$I$2:$I$501,$B$4,Cleaned_Data!$N$2:$N$501,$B$5,Cleaned_Data!$L$2:$L$501,$B$6) -> 7 | D132: =SUMIFS(Cleaned_Data!$F$2:$F$501,Cleaned_Data!$H$2:$H$501,$A132,Cleaned_Data!$D$2:$D$501,$B$3,Cleaned_Data!$I$2:$I$501,$B$4,Cleaned_Data!$N$2:$N$501,$B$5,Cleaned_Data!$L$2:$L$501,$B$6) -> 13 | E132: =IF($B$133=0,0,B132/$B$133) -> 0.012709054 | F132: =SUMIFS(Cleaned_Data!$G$2:$G$501,Cleaned_Data!$H$2:$H$501,$A132) -> 19887 | G132: =B132+ROW()/1000000 -> 19887
A133: Grand Total | B133: =SUM(B73:B132) -> 1564790 | C133: =SUM(C73:C132) -> 500 | D133: =SUM(D73:D132) -> 810 | E133: =SUM(E73:E132) -> 1 | F133: =SUM(F73:F132) -> 1564790

Sheet Cleaned_Data
A1: Order ID | B1: Date | C1: Product | D1: Category | E1: Price | F1: Quantity | G1: Total Sales | H1: Customer Name | I1: Customer Location | J1: Payment Method | K1: Order Status | L1: Month | M1: Day of Week | N1: Status Flag | O1: Validation
A2: =TRIM(Raw_Data!A2) -> AMZ-10052 | B2: =Raw_Data!B2 -> 46266 | C2: =PROPER(TRIM(Raw_Data!C2)) -> Mixer Grinder | D2: =TRIM(Raw_Data!D2) -> Home & Kitchen | E2: =Raw_Data!E2 -> 3499 | F2: =Raw_Data!F2 -> 1 | G2: =E2*F2 -> 3499 | H2: =PROPER(TRIM(Raw_Data!H2)) -> Vikram Joshi | I2: =PROPER(TRIM(Raw_Data!I2)) -> Hyderabad | J2: =TRIM(Raw_Data!J2) -> UPI | K2: =PROPER(TRIM(Raw_Data!K2)) -> Delivered | L2: =TEXT(B2,"MMM") -> Sep | M2: =TEXT(B2,"ddd") -> Tue | N2: =IF(K2="Delivered","Delivered",IF(K2="Cancelled","Cancelled","Pending")) -> Delivered | O2: =IF(ROUND(G2-Raw_Data!G2,2)=0,"OK","Corrected") -> OK
A3: =TRIM(Raw_Data!A3) -> AMZ-10123 | B3: =Raw_Data!B3 -> 46266 | C3: =PROPER(TRIM(Raw_Data!C3)) -> Self Help Book | D3: =TRIM(Raw_Data!D3) -> Books | E3: =Raw_Data!E3 -> 399 | F3: =Raw_Data!F3 -> 3 | G3: =E3*F3 -> 1197 | H3: =PROPER(TRIM(Raw_Data!H3)) -> Vikram Iyer | I3: =PROPER(TRIM(Raw_Data!I3)) -> Bangalore | J3: =TRIM(Raw_Data!J3) -> Debit Card | K3: =PROPER(TRIM(Raw_Data!K3)) -> Delivered | L3: =TEXT(B3,"MMM") -> Sep | M3: =TEXT(B3,"ddd") -> Tue | N3: =IF(K3="Delivered","Delivered",IF(K3="Cancelled","Cancelled","Pending")) -> Delivered | O3: =IF(ROUND(G3-Raw_Data!G3,2)=0,"OK","Corrected") -> OK
A4: =TRIM(Raw_Data!A4) -> AMZ-10196 | B4: =Raw_Data!B4 -> 46266 | C4: =PROPER(TRIM(Raw_Data!C4)) -> Water Bottle | D4: =TRIM(Raw_Data!D4) -> Home & Kitchen | E4: =Raw_Data!E4 -> 499 | F4: =Raw_Data!F4 -> 2 | G4: =E4*F4 -> 998 | H4: =PROPER(TRIM(Raw_Data!H4)) -> Priya Das | I4: =PROPER(TRIM(Raw_Data!I4)) -> Hyderabad | J4: =TRIM(Raw_Data!J4) -> Debit Card | K4: =PROPER(TRIM(Raw_Data!K4)) -> Delivered | L4: =TEXT(B4,"MMM") -> Sep | M4: =TEXT(B4,"ddd") -> Tue | N4: =IF(K4="Delivered","Delivered",IF(K4="Cancelled","Cancelled","Pending")) -> Delivered | O4: =IF(ROUND(G4-Raw_Data!G4,2)=0,"OK","Corrected") -> OK
A5: =TRIM(Raw_Data!A5) -> AMZ-10245 | B5: =Raw_Data!B5 -> 46266 | C5: =PROPER(TRIM(Raw_Data!C5)) -> Self Help Book | D5: =TRIM(Raw_Data!D5) -> Books | E5: =Raw_Data!E5 -> 399 | F5: =Raw_Data!F5 -> 3 | G5: =E5*F5 -> 1197 | H5: =PROPER(TRIM(Raw_Data!H5)) -> Vivaan Sharma | I5: =PROPER(TRIM(Raw_Data!I5)) -> Mumbai | J5: =TRIM(Raw_Data!J5) -> Credit Card | K5: =PROPER(TRIM(Raw_Data!K5)) -> Delivered | L5: =TEXT(B5,"MMM") -> Sep | M5: =TEXT(B5,"ddd") -> Tue | N5: =IF(K5="Delivered","Delivered",IF(K5="Cancelled","Cancelled","Pending")) -> Delivered | O5: =IF(ROUND(G5-Raw_Data!G5,2)=0,"OK","Corrected") -> OK
A6: =TRIM(Raw_Data!A6) -> AMZ-10252 | B6: =Raw_Data!B6 -> 46266 | C6: =PROPER(TRIM(Raw_Data!C6)) -> Cotton T-Shirt | D6: =TRIM(Raw_Data!D6) -> Clothing | E6: =Raw_Data!E6 -> 599 | F6: =Raw_Data!F6 -> 1 | G6: =E6*F6 -> 599 | H6: =PROPER(TRIM(Raw_Data!H6)) -> Priya Chopra | I6: =PROPER(TRIM(Raw_Data!I6)) -> Bangalore | J6: =TRIM(Raw_Data!J6) -> Debit Card | K6: =PROPER(TRIM(Raw_Data!K6)) -> Delivered | L6: =TEXT(B6,"MMM") -> Sep | M6: =TEXT(B6,"ddd") -> Tue | N6: =IF(K6="Delivered","Delivered",IF(K6="Cancelled","Cancelled","Pending")) -> Delivered | O6: =IF(ROUND(G6-Raw_Data!G6,2)=0,"OK","Corrected") -> OK
A7: =TRIM(Raw_Data!A7) -> AMZ-10255 | B7: =Raw_Data!B7 -> 46266 | C7: =PROPER(TRIM(Raw_Data!C7)) -> Sandals | D7: =TRIM(Raw_Data!D7) -> Footwear | E7: =Raw_Data!E7 -> 899 | F7: =Raw_Data!F7 -> 4 | G7: =E7*F7 -> 3596 | H7: =PROPER(TRIM(Raw_Data!H7)) -> Priya Das | I7: =PROPER(TRIM(Raw_Data!I7)) -> Hyderabad | J7: =TRIM(Raw_Data!J7) -> Credit Card | K7: =PROPER(TRIM(Raw_Data!K7)) -> Delivered | L7: =TEXT(B7,"MMM") -> Sep | M7: =TEXT(B7,"ddd") -> Tue | N7: =IF(K7="Delivered","Delivered",IF(K7="Cancelled","Cancelled","Pending")) -> Delivered | O7: =IF(ROUND(G7-Raw_Data!G7,2)=0,"OK","Corrected") -> OK
A8: =TRIM(Raw_Data!A9) -> AMZ-10301 | B8: =Raw_Data!B9 -> 46266 | C8: =PROPER(TRIM(Raw_Data!C9)) -> Sandals | D8: =TRIM(Raw_Data!D9) -> Footwear | E8: =Raw_Data!E9 -> 899 | F8: =Raw_Data!F9 -> 3 | G8: =E8*F8 -> 2697 | H8: =PROPER(TRIM(Raw_Data!H9)) -> Nikhil Reddy | I8: =PROPER(TRIM(Raw_Data!I9)) -> Chennai | J8: =TRIM(Raw_Data!J9) -> UPI | K8: =PROPER(TRIM(Raw_Data!K9)) -> Delivered | L8: =TEXT(B8,"MMM") -> Sep | M8: =TEXT(B8,"ddd") -> Tue | N8: =IF(K8="Delivered","Delivered",IF(K8="Cancelled","Cancelled","Pending")) -> Delivered | O8: =IF(ROUND(G8-Raw_Data!G9,2)=0,"OK","Corrected") -> OK
A9: =TRIM(Raw_Data!A11) -> AMZ-10364 | B9: =Raw_Data!B11 -> 46266 | C9: =PROPER(TRIM(Raw_Data!C11)) -> Water Bottle | D9: =TRIM(Raw_Data!D11) -> Home & Kitchen | E9: =Raw_Data!E11 -> 499 | F9: =Raw_Data!F11 -> 3 | G9: =E9*F9 -> 1497 | H9: =PROPER(TRIM(Raw_Data!H11)) -> Vivaan Das | I9: =PROPER(TRIM(Raw_Data!I11)) -> Ahmedabad | J9: =TRIM(Raw_Data!J11) -> UPI | K9: =PROPER(TRIM(Raw_Data!K11)) -> Delivered | L9: =TEXT(B9,"MMM") -> Sep | M9: =TEXT(B9,"ddd") -> Tue | N9: =IF(K9="Delivered","Delivered",IF(K9="Cancelled","Cancelled","Pending")) -> Delivered | O9: =IF(ROUND(G9-Raw_Data!G11,2)=0,"OK","Corrected") -> OK
A10: =TRIM(Raw_Data!A12) -> AMZ-10414 | B10: =Raw_Data!B12 -> 46266 | C10: =PROPER(TRIM(Raw_Data!C12)) -> Air Fryer | D10: =TRIM(Raw_Data!D12) -> Home & Kitchen | E10: =Raw_Data!E12 -> 5999 | F10: =Raw_Data!F12 -> 1 | G10: =E10*F10 -> 5999 | H10: =PROPER(TRIM(Raw_Data!H12)) -> Aditya Singh | I10: =PROPER(TRIM(Raw_Data!I12)) -> Delhi | J10: =TRIM(Raw_Data!J12) -> UPI | K10: =PROPER(TRIM(Raw_Data!K12)) -> Delivered | L10: =TEXT(B10,"MMM") -> Sep | M10: =TEXT(B10,"ddd") -> Tue | N10: =IF(K10="Delivered","Delivered",IF(K10="Cancelled","Cancelled","Pending")) -> Delivered | O10: =IF(ROUND(G10-Raw_Data!G12,2)=0,"OK","Corrected") -> OK
A11: =TRIM(Raw_Data!A13) -> AMZ-10484 | B11: =Raw_Data!B13 -> 46266 | C11: =PROPER(TRIM(Raw_Data!C13)) -> Water Bottle | D11: =TRIM(Raw_Data!D13) -> Home & Kitchen | E11: =Raw_Data!E13 -> 499 | F11: =Raw_Data!F13 -> 1 | G11: =E11*F11 -> 499 | H11: =PROPER(TRIM(Raw_Data!H13)) -> Priya Iyer | I11: =PROPER(TRIM(Raw_Data!I13)) -> Delhi | J11: =TRIM(Raw_Data!J13) -> Debit Card | K11: =PROPER(TRIM(Raw_Data!K13)) -> Delivered | L11: =TEXT(B11,"MMM") -> Sep | M11: =TEXT(B11,"ddd") -> Tue | N11: =IF(K11="Delivered","Delivered",IF(K11="Cancelled","Cancelled","Pending")) -> Delivered | O11: =IF(ROUND(G11-Raw_Data!G13,2)=0,"OK","Corrected") -> OK
A12: =TRIM(Raw_Data!A14) -> AMZ-10113 | B12: =Raw_Data!B14 -> 46267 | C12: =PROPER(TRIM(Raw_Data!C14)) -> Cotton T-Shirt | D12: =TRIM(Raw_Data!D14) -> Clothing | E12: =Raw_Data!E14 -> 599 | F12: =Raw_Data!F14 -> 2 | G12: =E12*F12 -> 1198 | H12: =PROPER(TRIM(Raw_Data!H14)) -> Aditya Rao | I12: =PROPER(TRIM(Raw_Data!I14)) -> Delhi | J12: =TRIM(Raw_Data!J14) -> UPI | K12: =PROPER(TRIM(Raw_Data!K14)) -> Delivered | L12: =TEXT(B12,"MMM") -> Sep | M12: =TEXT(B12,"ddd") -> Wed | N12: =IF(K12="Delivered","Delivered",IF(K12="Cancelled","Cancelled","Pending")) -> Delivered | O12: =IF(ROUND(G12-Raw_Data!G14,2)=0,"OK","Corrected") -> OK
A13: =TRIM(Raw_Data!A15) -> AMZ-10145 | B13: =Raw_Data!B15 -> 46267 | C13: =PROPER(TRIM(Raw_Data!C15)) -> Cotton T-Shirt | D13: =TRIM(Raw_Data!D15) -> Clothing | E13: =Raw_Data!E15 -> 599 | F13: =Raw_Data!F15 -> 1 | G13: =E13*F13 -> 599 | H13: =PROPER(TRIM(Raw_Data!H15)) -> Tanvi Joshi | I13: =PROPER(TRIM(Raw_Data!I15)) -> Bangalore | J13: =TRIM(Raw_Data!J15) -> UPI | K13: =PROPER(TRIM(Raw_Data!K15)) -> Delivered | L13: =TEXT(B13,"MMM") -> Sep | M13: =TEXT(B13,"ddd") -> Wed | N13: =IF(K13="Delivered","Delivered",IF(K13="Cancelled","Cancelled","Pending")) -> Delivered | O13: =IF(ROUND(G13-Raw_Data!G15,2)=0,"OK","Corrected") -> OK
A14: =TRIM(Raw_Data!A16) -> AMZ-10182 | B14: =Raw_Data!B16 -> 46267 | C14: =PROPER(TRIM(Raw_Data!C16)) -> Air Fryer | D14: =TRIM(Raw_Data!D16) -> Home & Kitchen | E14: =Raw_Data!E16 -> 5999 | F14: =Raw_Data!F16 -> 1 | G14: =E14*F14 -> 5999 | H14: =PROPER(TRIM(Raw_Data!H16)) -> Aarav Joshi | I14: =PROPER(TRIM(Raw_Data!I16)) -> Pune | J14: =TRIM(Raw_Data!J16) -> Net Banking | K14: =PROPER(TRIM(Raw_Data!K16)) -> Cancelled | L14: =TEXT(B14,"MMM") -> Sep | M14: =TEXT(B14,"ddd") -> Wed | N14: =IF(K14="Delivered","Delivered",IF(K14="Cancelled","Cancelled","Pending")) -> Cancelled | O14: =IF(ROUND(G14-Raw_Data!G16,2)=0,"OK","Corrected") -> OK
A15: =TRIM(Raw_Data!A17) -> AMZ-10204 | B15: =Raw_Data!B17 -> 46267 | C15: =PROPER(TRIM(Raw_Data!C17)) -> Mixer Grinder | D15: =TRIM(Raw_Data!D17) -> Home & Kitchen | E15: =Raw_Data!E17 -> 3499 | F15: =Raw_Data!F17 -> 1 | G15: =E15*F15 -> 3499 | H15: =PROPER(TRIM(Raw_Data!H17)) -> Kavya Patel | I15: =PROPER(TRIM(Raw_Data!I17)) -> Hyderabad | J15: =TRIM(Raw_Data!J17) -> UPI | K15: =PROPER(TRIM(Raw_Data!K17)) -> Shipped | L15: =TEXT(B15,"MMM") -> Sep | M15: =TEXT(B15,"ddd") -> Wed | N15: =IF(K15="Delivered","Delivered",IF(K15="Cancelled","Cancelled","Pending")) -> Pending | O15: =IF(ROUND(G15-Raw_Data!G17,2)=0,"OK","Corrected") -> OK
A16: =TRIM(Raw_Data!A18) -> AMZ-10237 | B16: =Raw_Data!B18 -> 46267 | C16: =PROPER(TRIM(Raw_Data!C18)) -> Self Help Book | D16: =TRIM(Raw_Data!D18) -> Books | E16: =Raw_Data!E18 -> 399 | F16: =Raw_Data!F18 -> 1 | G16: =E16*F16 -> 399 | H16: =PROPER(TRIM(Raw_Data!H18)) -> Nikhil Kulkarni | I16: =PROPER(TRIM(Raw_Data!I18)) -> Pune | J16: =TRIM(Raw_Data!J18) -> Credit Card | K16: =PROPER(TRIM(Raw_Data!K18)) -> Delivered | L16: =TEXT(B16,"MMM") -> Sep | M16: =TEXT(B16,"ddd") -> Wed | N16: =IF(K16="Delivered","Delivered",IF(K16="Cancelled","Cancelled","Pending")) -> Delivered | O16: =IF(ROUND(G16-Raw_Data!G18,2)=0,"OK","Corrected") -> OK
A17: =TRIM(Raw_Data!A19) -> AMZ-10260 | B17: =Raw_Data!B19 -> 46267 | C17: =PROPER(TRIM(Raw_Data!C19)) -> Wireless Earbuds | D17: =TRIM(Raw_Data!D19) -> Electronics | E17: =Raw_Data!E19 -> 2499 | F17: =Raw_Data!F19 -> 2 | G17: =E17*F17 -> 4998 | H17: =PROPER(TRIM(Raw_Data!H19)) -> Nikhil Patel | I17: =PROPER(TRIM(Raw_Data!I19)) -> Hyderabad | J17: =TRIM(Raw_Data!J19) -> UPI | K17: =PROPER(TRIM(Raw_Data!K19)) -> Delivered | L17: =TEXT(B17,"MMM") -> Sep | M17: =TEXT(B17,"ddd") -> Wed | N17: =IF(K17="Delivered","Delivered",IF(K17="Cancelled","Cancelled","Pending")) -> Delivered | O17: =IF(ROUND(G17-Raw_Data!G19,2)=0,"OK","Corrected") -> OK
A18: =TRIM(Raw_Data!A20) -> AMZ-10269 | B18: =Raw_Data!B20 -> 46267 | C18: =PROPER(TRIM(Raw_Data!C20)) -> Denim Jeans | D18: =TRIM(Raw_Data!D20) -> Clothing | E18: =Raw_Data!E20 -> 1799 | F18: =Raw_Data!F20 -> 1 | G18: =E18*F18 -> 1799 | H18: =PROPER(TRIM(Raw_Data!H20)) -> Tanvi Joshi | I18: =PROPER(TRIM(Raw_Data!I20)) -> Bangalore | J18: =TRIM(Raw_Data!J20) -> UPI | K18: =PROPER(TRIM(Raw_Data!K20)) -> Delivered | L18: =TEXT(B18,"MMM") -> Sep | M18: =TEXT(B18,"ddd") -> Wed | N18: =IF(K18="Delivered","Delivered",IF(K18="Cancelled","Cancelled","Pending")) -> Delivered | O18: =IF(ROUND(G18-Raw_Data!G20,2)=0,"OK","Corrected") -> OK
A19: =TRIM(Raw_Data!A21) -> AMZ-10272 | B19: =Raw_Data!B21 -> 46267 | C19: =PROPER(TRIM(Raw_Data!C21)) -> Running Shoes | D19: =TRIM(Raw_Data!D21) -> Footwear | E19: =Raw_Data!E21 -> 3299 | F19: =Raw_Data!F21 -> 1 | G19: =E19*F19 -> 3299 | H19: =PROPER(TRIM(Raw_Data!H21)) -> Priya Iyer | I19: =PROPER(TRIM(Raw_Data!I21)) -> Delhi | J19: =TRIM(Raw_Data!J21) -> Debit Card | K19: =PROPER(TRIM(Raw_Data!K21)) -> Delivered | L19: =TEXT(B19,"MMM") -> Sep | M19: =TEXT(B19,"ddd") -> Wed | N19: =IF(K19="Delivered","Delivered",IF(K19="Cancelled","Cancelled","Pending")) -> Delivered | O19: =IF(ROUND(G19-Raw_Data!G21,2)=0,"OK","Corrected") -> OK
A20: =TRIM(Raw_Data!A22) -> AMZ-10291 | B20: =Raw_Data!B22 -> 46267 | C20: =PROPER(TRIM(Raw_Data!C22)) -> Mixer Grinder | D20: =TRIM(Raw_Data!D22) -> Home & Kitchen | E20: =Raw_Data!E22 -> 3499 | F20: =Raw_Data!F22 -> 2 | G20: =E20*F20 -> 6998 | H20: =PROPER(TRIM(Raw_Data!H22)) -> Priya Iyer | I20: =PROPER(TRIM(Raw_Data!I22)) -> Delhi | J20: =TRIM(Raw_Data!J22) -> Cash On Delivery | K20: =PROPER(TRIM(Raw_Data!K22)) -> Delivered | L20: =TEXT(B20,"MMM") -> Sep | M20: =TEXT(B20,"ddd") -> Wed | N20: =IF(K20="Delivered","Delivered",IF(K20="Cancelled","Cancelled","Pending")) -> Delivered | O20: =IF(ROUND(G20-Raw_Data!G22,2)=0,"OK","Corrected") -> OK
... A63: =TRIM(Raw_Data!A65) -> AMZ-10317 | B63: =Raw_Data!B65 -> 46269 | C63: =PROPER(TRIM(Raw_Data!C65)) -> Power Bank | D63: =TRIM(Raw_Data!D65) -> Electronics | E63: =Raw_Data!E65 -> 1299 | F63: =Raw_Data!F65 -> 1 | G63: =E63*F63 -> 1299 | H63: =PROPER(TRIM(Raw_Data!H65)) -> Sneha Reddy | I63: =PROPER(TRIM(Raw_Data!I65)) -> Pune | J63: =TRIM(Raw_Data!J65) -> UPI | K63: =PROPER(TRIM(Raw_Data!K65)) -> Delivered | L63: =TEXT(B63,"MMM") -> Sep | M63: =TEXT(B63,"ddd") -> Fri | N63: =IF(K63="Delivered","Delivered",IF(K63="Cancelled","Cancelled","Pending")) -> Delivered | O63: =IF(ROUND(G63-Raw_Data!G65,2)=0,"OK","Corrected") -> OK
A64: =TRIM(Raw_Data!A67) -> AMZ-10363 | B64: =Raw_Data!B67 -> 46269 | C64: =PROPER(TRIM(Raw_Data!C67)) -> Bluetooth Speaker | D64: =TRIM(Raw_Data!D67) -> Electronics | E64: =Raw_Data!E67 -> 1999 | F64: =Raw_Data!F67 -> 3 | G64: =E64*F64 -> 5997 | H64: =PROPER(TRIM(Raw_Data!H67)) -> Tanvi Gupta | I64: =PROPER(TRIM(Raw_Data!I67)) -> Hyderabad | J64: =TRIM(Raw_Data!J67) -> UPI | K64: =PROPER(TRIM(Raw_Data!K67)) -> Delivered | L64: =TEXT(B64,"MMM") -> Sep | M64: =TEXT(B64,"ddd") -> Fri | N64: =IF(K64="Delivered","Delivered",IF(K64="Cancelled","Cancelled","Pending")) -> Delivered | O64: =IF(ROUND(G64-Raw_Data!G67,2)=0,"OK","Corrected") -> OK
A65: =TRIM(Raw_Data!A68) -> AMZ-10379 | B65: =Raw_Data!B68 -> 46269 | C65: =PROPER(TRIM(Raw_Data!C68)) -> Bluetooth Speaker | D65: =TRIM(Raw_Data!D68) -> Electronics | E65: =Raw_Data!E68 -> 1999 | F65: =Raw_Data!F68 -> 1 | G65: =E65*F65 -> 1999 | H65: =PROPER(TRIM(Raw_Data!H68)) -> Suresh Nair | I65: =PROPER(TRIM(Raw_Data!I68)) -> Bangalore | J65: =TRIM(Raw_Data!J68) -> Debit Card | K65: =PROPER(TRIM(Raw_Data!K68)) -> Delivered | L65: =TEXT(B65,"MMM") -> Sep | M65: =TEXT(B65,"ddd") -> Fri | N65: =IF(K65="Delivered","Delivered",IF(K65="Cancelled","Cancelled","Pending")) -> Delivered | O65: =IF(ROUND(G65-Raw_Data!G68,2)=0,"OK","Corrected") -> OK
A66: =TRIM(Raw_Data!A69) -> AMZ-10382 | B66: =Raw_Data!B69 -> 46269 | C66: =PROPER(TRIM(Raw_Data!C69)) -> Running Shoes | D66: =TRIM(Raw_Data!D69) -> Footwear | E66: =Raw_Data!E69 -> 3299 | F66: =Raw_Data!F69 -> 3 | G66: =E66*F66 -> 9897 | H66: =PROPER(TRIM(Raw_Data!H69)) -> Nikhil Patel | I66: =PROPER(TRIM(Raw_Data!I69)) -> Hyderabad | J66: =TRIM(Raw_Data!J69) -> Cash On Delivery | K66: =PROPER(TRIM(Raw_Data!K69)) -> Delivered | L66: =TEXT(B66,"MMM") -> Sep | M66: =TEXT(B66,"ddd") -> Fri | N66: =IF(K66="Delivered","Delivered",IF(K66="Cancelled","Cancelled","Pending")) -> Delivered | O66: =IF(ROUND(G66-Raw_Data!G69,2)=0,"OK","Corrected") -> OK
A67: =TRIM(Raw_Data!A70) -> AMZ-10412 | B67: =Raw_Data!B70 -> 46269 | C67: =PROPER(TRIM(Raw_Data!C70)) -> Smart Watch | D67: =TRIM(Raw_Data!D70) -> Electronics | E67: =Raw_Data!E70 -> 4999 | F67: =Raw_Data!F70 -> 1 | G67: =E67*F67 -> 4999 | H67: =PROPER(TRIM(Raw_Data!H70)) -> Meera Singh | I67: =PROPER(TRIM(Raw_Data!I70)) -> Hyderabad | J67: =TRIM(Raw_Data!J70) -> UPI | K67: =PROPER(TRIM(Raw_Data!K70)) -> Shipped | L67: =TEXT(B67,"MMM") -> Sep | M67: =TEXT(B67,"ddd") -> Fri | N67: =IF(K67="Delivered","Delivered",IF(K67="Cancelled","Cancelled","Pending")) -> Pending | O67: =IF(ROUND(G67-Raw_Data!G70,2)=0,"OK","Corrected") -> OK
A68: =TRIM(Raw_Data!A71) -> AMZ-10482 | B68: =Raw_Data!B71 -> 46269 | C68: =PROPER(TRIM(Raw_Data!C71)) -> Power Bank | D68: =TRIM(Raw_Data!D71) -> Electronics | E68: =Raw_Data!E71 -> 1299 | F68: =Raw_Data!F71 -> 1 | G68: =E68*F68 -> 1299 | H68: =PROPER(TRIM(Raw_Data!H71)) -> Tanvi Verma | I68: =PROPER(TRIM(Raw_Data!I71)) -> Kolkata | J68: =TRIM(Raw_Data!J71) -> UPI | K68: =PROPER(TRIM(Raw_Data!K71)) -> Delivered | L68: =TEXT(B68,"MMM") -> Sep | M68: =TEXT(B68,"ddd") -> Fri | N68: =IF(K68="Delivered","Delivered",IF(K68="Cancelled","Cancelled","Pending")) -> Delivered | O68: =IF(ROUND(G68-Raw_Data!G71,2)=0,"OK","Corrected") -> OK
A69: =TRIM(Raw_Data!A72) -> AMZ-10486 | B69: =Raw_Data!B72 -> 46269 | C69: =PROPER(TRIM(Raw_Data!C72)) -> Casual Sneakers | D69: =TRIM(Raw_Data!D72) -> Footwear | E69: =Raw_Data!E72 -> 2199 | F69: =Raw_Data!F72 -> 1 | G69: =E69*F69 -> 2199 | H69: =PROPER(TRIM(Raw_Data!H72)) -> Vivaan Iyer | I69: =PROPER(TRIM(Raw_Data!I72)) -> Pune | J69: =TRIM(Raw_Data!J72) -> UPI | K69: =PROPER(TRIM(Raw_Data!K72)) -> Delivered | L69: =TEXT(B69,"MMM") -> Sep | M69: =TEXT(B69,"ddd") -> Fri | N69: =IF(K69="Delivered","Delivered",IF(K69="Cancelled","Cancelled","Pending")) -> Delivered | O69: =IF(ROUND(G69-Raw_Data!G72,2)=0,"OK","Corrected") -> OK
A70: =TRIM(Raw_Data!A73) -> AMZ-10491 | B70: =Raw_Data!B73 -> 46269 | C70: =PROPER(TRIM(Raw_Data!C73)) -> Self Help Book | D70: =TRIM(Raw_Data!D73) -> Books | E70: =Raw_Data!E73 -> 399 | F70: =Raw_Data!F73 -> 1 | G70: =E70*F70 -> 399 | H70: =PROPER(TRIM(Raw_Data!H73)) -> Neha Kulkarni | I70: =PROPER(TRIM(Raw_Data!I73)) -> Delhi | J70: =TRIM(Raw_Data!J73) -> UPI | K70: =PROPER(TRIM(Raw_Data!K73)) -> Delivered | L70: =TEXT(B70,"MMM") -> Sep | M70: =TEXT(B70,"ddd") -> Fri | N70: =IF(K70="Delivered","Delivered",IF(K70="Cancelled","Cancelled","Pending")) -> Delivered | O70: =IF(ROUND(G70-Raw_Data!G73,2)=0,"OK","Corrected") -> OK
A71: =TRIM(Raw_Data!A74) -> AMZ-10500 | B71: =Raw_Data!B74 -> 46269 | C71: =PROPER(TRIM(Raw_Data!C74)) -> Wireless Earbuds | D71: =TRIM(Raw_Data!D74) -> Electronics | E71: =Raw_Data!E74 -> 2499 | F71: =Raw_Data!F74 -> 1 | G71: =E71*F71 -> 2499 | H71: =PROPER(TRIM(Raw_Data!H74)) -> Nikhil Joshi | I71: =PROPER(TRIM(Raw_Data!I74)) -> Lucknow | J71: =TRIM(Raw_Data!J74) -> Credit Card | K71: =PROPER(TRIM(Raw_Data!K74)) -> Delivered | L71: =TEXT(B71,"MMM") -> Sep | M71: =TEXT(B71,"ddd") -> Fri | N71: =IF(K71="Delivered","Delivered",IF(K71="Cancelled","Cancelled","Pending")) -> Delivered | O71: =IF(ROUND(G71-Raw_Data!G74,2)=0,"OK","Corrected") -> OK
A72: =TRIM(Raw_Data!A75) -> AMZ-10002 | B72: =Raw_Data!B75 -> 46270 | C72: =PROPER(TRIM(Raw_Data!C75)) -> Denim Jeans | D72: =TRIM(Raw_Data!D75) -> Clothing | E72: =Raw_Data!E75 -> 1799 | F72: =Raw_Data!F75 -> 1 | G72: =E72*F72 -> 1799 | H72: =PROPER(TRIM(Raw_Data!H75)) -> Anjali Verma | I72: =PROPER(TRIM(Raw_Data!I75)) -> Mumbai | J72: =TRIM(Raw_Data!J75) -> Debit Card | K72: =PROPER(TRIM(Raw_Data!K75)) -> Shipped | L72: =TEXT(B72,"MMM") -> Sep | M72: =TEXT(B72,"ddd") -> Sat | N72: =IF(K72="Delivered","Delivered",IF(K72="Cancelled","Cancelled","Pending")) -> Pending | O72: =IF(ROUND(G72-Raw_Data!G75,2)=0,"OK","Corrected") -> OK
A73: =TRIM(Raw_Data!A77) -> AMZ-10008 | B73: =Raw_Data!B77 -> 46270 | C73: =PROPER(TRIM(Raw_Data!C77)) -> Power Bank | D73: =TRIM(Raw_Data!D77) -> Electronics | E73: =Raw_Data!E77 -> 1299 | F73: =Raw_Data!F77 -> 1 | G73: =E73*F73 -> 1299 | H73: =PROPER(TRIM(Raw_Data!H77)) -> Priya Chopra | I73: =PROPER(TRIM(Raw_Data!I77)) -> Bangalore | J73: =TRIM(Raw_Data!J77) -> Debit Card | K73: =PROPER(TRIM(Raw_Data!K77)) -> Pending | L73: =TEXT(B73,"MMM") -> Sep | M73: =TEXT(B73,"ddd") -> Sat | N73: =IF(K73="Delivered","Delivered",IF(K73="Cancelled","Cancelled","Pending")) -> Pending | O73: =IF(ROUND(G73-Raw_Data!G77,2)=0,"OK","Corrected") -> OK
A74: =TRIM(Raw_Data!A78) -> AMZ-10029 | B74: =Raw_Data!B78 -> 46270 | C74: =PROPER(TRIM(Raw_Data!C78)) -> Smart Watch | D74: =TRIM(Raw_Data!D78) -> Electronics | E74: =Raw_Data!E78 -> 4999 | F74: =Raw_Data!F78 -> 1 | G74: =E74*F74 -> 4999 | H74: =PROPER(TRIM(Raw_Data!H78)) -> Priya Das | I74: =PROPER(TRIM(Raw_Data!I78)) -> Hyderabad | J74: =TRIM(Raw_Data!J78) -> UPI | K74: =PROPER(TRIM(Raw_Data!K78)) -> Delivered | L74: =TEXT(B74,"MMM") -> Sep | M74: =TEXT(B74,"ddd") -> Sat | N74: =IF(K74="Delivered","Delivered",IF(K74="Cancelled","Cancelled","Pending")) -> Delivered | O74: =IF(ROUND(G74-Raw_Data!G78,2)=0,"OK","Corrected") -> OK
A75: =TRIM(Raw_Data!A79) -> AMZ-10037 | B75: =Raw_Data!B79 -> 46270 | C75: =PROPER(TRIM(Raw_Data!C79)) -> Cotton T-Shirt | D75: =TRIM(Raw_Data!D79) -> Clothing | E75: =Raw_Data!E79 -> 599 | F75: =Raw_Data!F79 -> 4 | G75: =E75*F75 -> 2396 | H75: =PROPER(TRIM(Raw_Data!H79)) -> Suresh Nair | I75: =PROPER(TRIM(Raw_Data!I79)) -> Bangalore | J75: =TRIM(Raw_Data!J79) -> Net Banking | K75: =PROPER(TRIM(Raw_Data!K79)) -> Delivered | L75: =TEXT(B75,"MMM") -> Sep | M75: =TEXT(B75,"ddd") -> Sat | N75: =IF(K75="Delivered","Delivered",IF(K75="Cancelled","Cancelled","Pending")) -> Delivered | O75: =IF(ROUND(G75-Raw_Data!G79,2)=0,"OK","Corrected") -> OK
A76: =TRIM(Raw_Data!A80) -> AMZ-10056 | B76: =Raw_Data!B80 -> 46270 | C76: =PROPER(TRIM(Raw_Data!C80)) -> Water Bottle | D76: =TRIM(Raw_Data!D80) -> Home & Kitchen | E76: =Raw_Data!E80 -> 499 | F76: =Raw_Data!F80 -> 1 | G76: =E76*F76 -> 499 | H76: =PROPER(TRIM(Raw_Data!H80)) -> Arjun Verma | I76: =PROPER(TRIM(Raw_Data!I80)) -> Pune | J76: =TRIM(Raw_Data!J80) -> UPI | K76: =PROPER(TRIM(Raw_Data!K80)) -> Delivered | L76: =TEXT(B76,"MMM") -> Sep | M76: =TEXT(B76,"ddd") -> Sat | N76: =IF(K76="Delivered","Delivered",IF(K76="Cancelled","Cancelled","Pending")) -> Delivered | O76: =IF(ROUND(G76-Raw_Data!G80,2)=0,"OK","Corrected") -> OK
A77: =TRIM(Raw_Data!A81) -> AMZ-10100 | B77: =Raw_Data!B81 -> 46270 | C77: =PROPER(TRIM(Raw_Data!C81)) -> Bluetooth Speaker | D77: =TRIM(Raw_Data!D81) -> Electronics | E77: =Raw_Data!E81 -> 1999 | F77: =Raw_Data!F81 -> 1 | G77: =E77*F77 -> 1999 | H77: =PROPER(TRIM(Raw_Data!H81)) -> Priya Chopra | I77: =PROPER(TRIM(Raw_Data!I81)) -> Bangalore | J77: =TRIM(Raw_Data!J81) -> UPI | K77: =PROPER(TRIM(Raw_Data!K81)) -> Shipped | L77: =TEXT(B77,"MMM") -> Sep | M77: =TEXT(B77,"ddd") -> Sat | N77: =IF(K77="Delivered","Delivered",IF(K77="Cancelled","Cancelled","Pending")) -> Pending | O77: =IF(ROUND(G77-Raw_Data!G81,2)=0,"OK","Corrected") -> OK
A78: =TRIM(Raw_Data!A82) -> AMZ-10104 | B78: =Raw_Data!B82 -> 46270 | C78: =PROPER(TRIM(Raw_Data!C82)) -> Wireless Earbuds | D78: =TRIM(Raw_Data!D82) -> Electronics | E78: =Raw_Data!E82 -> 2499 | F78: =Raw_Data!F82 -> 2 | G78: =E78*F78 -> 4998 | H78: =PROPER(TRIM(Raw_Data!H82)) -> Aditya Kulkarni | I78: =PROPER(TRIM(Raw_Data!I82)) -> Bangalore | J78: =TRIM(Raw_Data!J82) -> UPI | K78: =PROPER(TRIM(Raw_Data!K82)) -> Delivered | L78: =TEXT(B78,"MMM") -> Sep | M78: =TEXT(B78,"ddd") -> Sat | N78: =IF(K78="Delivered","Delivered",IF(K78="Cancelled","Cancelled","Pending")) -> Delivered | O78: =IF(ROUND(G78-Raw_Data!G82,2)=0,"OK","Corrected") -> OK
A79: =TRIM(Raw_Data!A83) -> AMZ-10125 | B79: =Raw_Data!B83 -> 46270 | C79: =PROPER(TRIM(Raw_Data!C83)) -> Python Programming Book | D79: =TRIM(Raw_Data!D83) -> Books | E79: =Raw_Data!E83 -> 699 | F79: =Raw_Data!F83 -> 1 | G79: =E79*F79 -> 699 | H79: =PROPER(TRIM(Raw_Data!H83)) -> Priya Das | I79: =PROPER(TRIM(Raw_Data!I83)) -> Hyderabad | J79: =TRIM(Raw_Data!J83) -> Net Banking | K79: =PROPER(TRIM(Raw_Data!K83)) -> Delivered | L79: =TEXT(B79,"MMM") -> Sep | M79: =TEXT(B79,"ddd") -> Sat | N79: =IF(K79="Delivered","Delivered",IF(K79="Cancelled","Cancelled","Pending")) -> Delivered | O79: =IF(ROUND(G79-Raw_Data!G83,2)=0,"OK","Corrected") -> OK
A80: =TRIM(Raw_Data!A84) -> AMZ-10133 | B80: =Raw_Data!B84 -> 46270 | C80: =PROPER(TRIM(Raw_Data!C84)) -> Mixer Grinder | D80: =TRIM(Raw_Data!D84) -> Home & Kitchen | E80: =Raw_Data!E84 -> 3499 | F80: =Raw_Data!F84 -> 2 | G80: =E80*F80 -> 6998 | H80: =PROPER(TRIM(Raw_Data!H84)) -> Vikram Reddy | I80: =PROPER(TRIM(Raw_Data!I84)) -> Hyderabad | J80: =TRIM(Raw_Data!J84) -> Credit Card | K80: =PROPER(TRIM(Raw_Data!K84)) -> Delivered | L80: =TEXT(B80,"MMM") -> Sep | M80: =TEXT(B80,"ddd") -> Sat | N80: =IF(K80="Delivered","Delivered",IF(K80="Cancelled","Cancelled","Pending")) -> Delivered | O80: =IF(ROUND(G80-Raw_Data!G84,2)=0,"OK","Corrected") -> OK
A81: =TRIM(Raw_Data!A85) -> AMZ-10161 | B81: =Raw_Data!B85 -> 46270 | C81: =PROPER(TRIM(Raw_Data!C85)) -> Self Help Book | D81: =TRIM(Raw_Data!D85) -> Books | E81: =Raw_Data!E85 -> 399 | F81: =Raw_Data!F85 -> 1 | G81: =E81*F81 -> 399 | H81: =PROPER(TRIM(Raw_Data!H85)) -> Aditya Rao | I81: =PROPER(TRIM(Raw_Data!I85)) -> Delhi | J81: =TRIM(Raw_Data!J85) -> Debit Card | K81: =PROPER(TRIM(Raw_Data!K85)) -> Delivered | L81: =TEXT(B81,"MMM") -> Sep | M81: =TEXT(B81,"ddd") -> Sat | N81: =IF(K81="Delivered","Delivered",IF(K81="Cancelled","Cancelled","Pending")) -> Delivered | O81: =IF(ROUND(G81-Raw_Data!G85,2)=0,"OK","Corrected") -> OK
A82: =TRIM(Raw_Data!A86) -> AMZ-10176 | B82: =Raw_Data!B86 -> 46270 | C82: =PROPER(TRIM(Raw_Data!C86)) -> Self Help Book | D82: =TRIM(Raw_Data!D86) -> Books | E82: =Raw_Data!E86 -> 399 | F82: =Raw_Data!F86 -> 1 | G82: =E82*F82 -> 399 | H82: =PROPER(TRIM(Raw_Data!H86)) -> Tanvi Iyer | I82: =PROPER(TRIM(Raw_Data!I86)) -> Kolkata | J82: =TRIM(Raw_Data!J86) -> Cash On Delivery | K82: =PROPER(TRIM(Raw_Data!K86)) -> Delivered | L82: =TEXT(B82,"MMM") -> Sep | M82: =TEXT(B82,"ddd") -> Sat | N82: =IF(K82="Delivered","Delivered",IF(K82="Cancelled","Cancelled","Pending")) -> Delivered | O82: =IF(ROUND(G82-Raw_Data!G86,2)=0,"OK","Corrected") -> OK
A83: =TRIM(Raw_Data!A87) -> AMZ-10179 | B83: =Raw_Data!B87 -> 46270 | C83: =PROPER(TRIM(Raw_Data!C87)) -> Running Shoes | D83: =TRIM(Raw_Data!D87) -> Footwear | E83: =Raw_Data!E87 -> 3299 | F83: =Raw_Data!F87 -> 1 | G83: =E83*F83 -> 3299 | H83: =PROPER(TRIM(Raw_Data!H87)) -> Aditya Kulkarni | I83: =PROPER(TRIM(Raw_Data!I87)) -> Bangalore | J83: =TRIM(Raw_Data!J87) -> Debit Card | K83: =PROPER(TRIM(Raw_Data!K87)) -> Delivered | L83: =TEXT(B83,"MMM") -> Sep | M83: =TEXT(B83,"ddd") -> Sat | N83: =IF(K83="Delivered","Delivered",IF(K83="Cancelled","Cancelled","Pending")) -> Delivered | O83: =IF(ROUND(G83-Raw_Data!G87,2)=0,"OK","Corrected") -> OK
A84: =TRIM(Raw_Data!A88) -> AMZ-10248 | B84: =Raw_Data!B88 -> 46270 | C84: =PROPER(TRIM(Raw_Data!C88)) -> Cotton T-Shirt | D84: =TRIM(Raw_Data!D88) -> Clothing | E84: =Raw_Data!E88 -> 599 | F84: =Raw_Data!F88 -> 1 | G84: =E84*F84 -> 599 | H84: =PROPER(TRIM(Raw_Data!H88)) -> Vikram Joshi | I84: =PROPER(TRIM(Raw_Data!I88)) -> Hyderabad | J84: =TRIM(Raw_Data!J88) -> Debit Card | K84: =PROPER(TRIM(Raw_Data!K88)) -> Delivered | L84: =TEXT(B84,"MMM") -> Sep | M84: =TEXT(B84,"ddd") -> Sat | N84: =IF(K84="Delivered","Delivered",IF(K84="Cancelled","Cancelled","Pending")) -> Delivered | O84: =IF(ROUND(G84-Raw_Data!G88,2)=0,"OK","Corrected") -> OK
A85: =TRIM(Raw_Data!A89) -> AMZ-10271 | B85: =Raw_Data!B89 -> 46270 | C85: =PROPER(TRIM(Raw_Data!C89)) -> Mixer Grinder | D85: =TRIM(Raw_Data!D89) -> Home & Kitchen | E85: =Raw_Data!E89 -> 3499 | F85: =Raw_Data!F89 -> 2 | G85: =E85*F85 -> 6998 | H85: =PROPER(TRIM(Raw_Data!H89)) -> Aditya Iyer | I85: =PROPER(TRIM(Raw_Data!I89)) -> Mumbai | J85: =TRIM(Raw_Data!J89) -> UPI | K85: =PROPER(TRIM(Raw_Data!K89)) -> Cancelled | L85: =TEXT(B85,"MMM") -> Sep | M85: =TEXT(B85,"ddd") -> Sat | N85: =IF(K85="Delivered","Delivered",IF(K85="Cancelled","Cancelled","Pending")) -> Cancelled | O85: =IF(ROUND(G85-Raw_Data!G89,2)=0,"OK","Corrected") -> OK
A86: =TRIM(Raw_Data!A91) -> AMZ-10298 | B86: =Raw_Data!B91 -> 46270 | C86: =PROPER(TRIM(Raw_Data!C91)) -> Sandals | D86: =TRIM(Raw_Data!D91) -> Footwear | E86: =Raw_Data!E91 -> 899 | F86: =Raw_Data!F91 -> 1 | G86: =E86*F86 -> 899 | H86: =PROPER(TRIM(Raw_Data!H91)) -> Ishaan Gupta | I86: =PROPER(TRIM(Raw_Data!I91)) -> Lucknow | J86: =TRIM(Raw_Data!J91) -> UPI | K86: =PROPER(TRIM(Raw_Data!K91)) -> Delivered | L86: =TEXT(B86,"MMM") -> Sep | M86: =TEXT(B86,"ddd") -> Sat | N86: =IF(K86="Delivered","Delivered",IF(K86="Cancelled","Cancelled","Pending")) -> Delivered | O86: =IF(ROUND(G86-Raw_Data!G91,2)=0,"OK","Corrected") -> OK
A87: =TRIM(Raw_Data!A92) -> AMZ-10326 | B87: =Raw_Data!B92 -> 46270 | C87: =PROPER(TRIM(Raw_Data!C92)) -> Self Help Book | D87: =TRIM(Raw_Data!D92) -> Books | E87: =Raw_Data!E92 -> 399 | F87: =Raw_Data!F92 -> 4 | G87: =E87*F87 -> 1596 | H87: =PROPER(TRIM(Raw_Data!H92)) -> Tanvi Verma | I87: =PROPER(TRIM(Raw_Data!I92)) -> Kolkata | J87: =TRIM(Raw_Data!J92) -> UPI | K87: =PROPER(TRIM(Raw_Data!K92)) -> Delivered | L87: =TEXT(B87,"MMM") -> Sep | M87: =TEXT(B87,"ddd") -> Sat | N87: =IF(K87="Delivered","Delivered",IF(K87="Cancelled","Cancelled","Pending")) -> Delivered | O87: =IF(ROUND(G87-Raw_Data!G92,2)=0,"OK","Corrected") -> OK
A88: =TRIM(Raw_Data!A93) -> AMZ-10390 | B88: =Raw_Data!B93 -> 46270 | C88: =PROPER(TRIM(Raw_Data!C93)) -> Water Bottle | D88: =TRIM(Raw_Data!D93) -> Home & Kitchen | E88: =Raw_Data!E93 -> 499 | F88: =Raw_Data!F93 -> 2 | G88: =E88*F88 -> 998 | H88: =PROPER(TRIM(Raw_Data!H93)) -> Neha Patel | I88: =PROPER(TRIM(Raw_Data!I93)) -> Bangalore | J88: =TRIM(Raw_Data!J93) -> Cash On Delivery | K88: =PROPER(TRIM(Raw_Data!K93)) -> Delivered | L88: =TEXT(B88,"MMM") -> Sep | M88: =TEXT(B88,"ddd") -> Sat | N88: =IF(K88="Delivered","Delivered",IF(K88="Cancelled","Cancelled","Pending")) -> Delivered | O88: =IF(ROUND(G88-Raw_Data!G93,2)=0,"OK","Corrected") -> OK
A89: =TRIM(Raw_Data!A94) -> AMZ-10411 | B89: =Raw_Data!B94 -> 46270 | C89: =PROPER(TRIM(Raw_Data!C94)) -> Power Bank | D89: =TRIM(Raw_Data!D94) -> Electronics | E89: =Raw_Data!E94 -> 1299 | F89: =Raw_Data!F94 -> 1 | G89: =E89*F89 -> 1299 | H89: =PROPER(TRIM(Raw_Data!H94)) -> Karan Joshi | I89: =PROPER(TRIM(Raw_Data!I94)) -> Hyderabad | J89: =TRIM(Raw_Data!J94) -> UPI | K89: =PROPER(TRIM(Raw_Data!K94)) -> Cancelled | L89: =TEXT(B89,"MMM") -> Sep | M89: =TEXT(B89,"ddd") -> Sat | N89: =IF(K89="Delivered","Delivered",IF(K89="Cancelled","Cancelled","Pending")) -> Cancelled | O89: =IF(ROUND(G89-Raw_Data!G94,2)=0,"OK","Corrected") -> OK
A90: =TRIM(Raw_Data!A95) -> AMZ-10413 | B90: =Raw_Data!B95 -> 46270 | C90: =PROPER(TRIM(Raw_Data!C95)) -> Casual Sneakers | D90: =TRIM(Raw_Data!D95) -> Footwear | E90: =Raw_Data!E95 -> 2199 | F90: =Raw_Data!F95 -> 2 | G90: =E90*F90 -> 4398 | H90: =PROPER(TRIM(Raw_Data!H95)) -> Aditya Singh | I90: =PROPER(TRIM(Raw_Data!I95)) -> Delhi | J90: =TRIM(Raw_Data!J95) -> UPI | K90: =PROPER(TRIM(Raw_Data!K95)) -> Delivered | L90: =TEXT(B90,"MMM") -> Sep | M90: =TEXT(B90,"ddd") -> Sat | N90: =IF(K90="Delivered","Delivered",IF(K90="Cancelled","Cancelled","Pending")) -> Delivered | O90: =IF(ROUND(G90-Raw_Data!G95,2)=0,"OK","Corrected") -> OK
A91: =TRIM(Raw_Data!A96) -> AMZ-10417 | B91: =Raw_Data!B96 -> 46270 | C91: =PROPER(TRIM(Raw_Data!C96)) -> Air Fryer | D91: =TRIM(Raw_Data!D96) -> Home & Kitchen | E91: =Raw_Data!E96 -> 5999 | F91: =Raw_Data!F96 -> 2 | G91: =E91*F91 -> 11998 | H91: =PROPER(TRIM(Raw_Data!H96)) -> Arjun Das | I91: =PROPER(TRIM(Raw_Data!I96)) -> Mumbai | J91: =TRIM(Raw_Data!J96) -> UPI | K91: =PROPER(TRIM(Raw_Data!K96)) -> Delivered | L91: =TEXT(B91,"MMM") -> Sep | M91: =TEXT(B91,"ddd") -> Sat | N91: =IF(K91="Delivered","Delivered",IF(K91="Cancelled","Cancelled","Pending")) -> Delivered | O91: =IF(ROUND(G91-Raw_Data!G96,2)=0,"OK","Corrected") -> OK
A92: =TRIM(Raw_Data!A98) -> AMZ-10437 | B92: =Raw_Data!B98 -> 46270 | C92: =PROPER(TRIM(Raw_Data!C98)) -> Denim Jeans | D92: =TRIM(Raw_Data!D98) -> Clothing | E92: =Raw_Data!E98 -> 1799 | F92: =Raw_Data!F98 -> 1 | G92: =E92*F92 -> 1799 | H92: =PROPER(TRIM(Raw_Data!H98)) -> Suresh Das | I92: =PROPER(TRIM(Raw_Data!I98)) -> Bangalore | J92: =TRIM(Raw_Data!J98) -> UPI | K92: =PROPER(TRIM(Raw_Data!K98)) -> Delivered | L92: =TEXT(B92,"MMM") -> Sep | M92: =TEXT(B92,"ddd") -> Sat | N92: =IF(K92="Delivered","Delivered",IF(K92="Cancelled","Cancelled","Pending")) -> Delivered | O92: =IF(ROUND(G92-Raw_Data!G98,2)=0,"OK","Corrected") -> OK
A93: =TRIM(Raw_Data!A99) -> AMZ-10465 | B93: =Raw_Data!B99 -> 46270 | C93: =PROPER(TRIM(Raw_Data!C99)) -> Denim Jeans | D93: =TRIM(Raw_Data!D99) -> Clothing | E93: =Raw_Data!E99 -> 1799 | F93: =Raw_Data!F99 -> 2 | G93: =E93*F93 -> 3598 | H93: =PROPER(TRIM(Raw_Data!H99)) -> Aditya Singh | I93: =PROPER(TRIM(Raw_Data!I99)) -> Delhi | J93: =TRIM(Raw_Data!J99) -> Net Banking | K93: =PROPER(TRIM(Raw_Data!K99)) -> Cancelled | L93: =TEXT(B93,"MMM") -> Sep | M93: =TEXT(B93,"ddd") -> Sat | N93: =IF(K93="Delivered","Delivered",IF(K93="Cancelled","Cancelled","Pending")) -> Cancelled | O93: =IF(ROUND(G93-Raw_Data!G99,2)=0,"OK","Corrected") -> OK
A94: =TRIM(Raw_Data!A100) -> AMZ-10485 | B94: =Raw_Data!B100 -> 46270 | C94: =PROPER(TRIM(Raw_Data!C100)) -> Running Shoes | D94: =TRIM(Raw_Data!D100) -> Footwear | E94: =Raw_Data!E100 -> 3299 | F94: =Raw_Data!F100 -> 1 | G94: =E94*F94 -> 3299 | H94: =PROPER(TRIM(Raw_Data!H100)) -> Suresh Nair | I94: =PROPER(TRIM(Raw_Data!I100)) -> Bangalore | J94: =TRIM(Raw_Data!J100) -> Cash On Delivery | K94: =PROPER(TRIM(Raw_Data!K100)) -> Delivered | L94: =TEXT(B94,"MMM") -> Sep | M94: =TEXT(B94,"ddd") -> Sat | N94: =IF(K94="Delivered","Delivered",IF(K94="Cancelled","Cancelled","Pending")) -> Delivered | O94: =IF(ROUND(G94-Raw_Data!G100,2)=0,"OK","Corrected") -> OK
A95: =TRIM(Raw_Data!A101) -> AMZ-10020 | B95: =Raw_Data!B101 -> 46271 | C95: =PROPER(TRIM(Raw_Data!C101)) -> Wireless Earbuds | D95: =TRIM(Raw_Data!D101) -> Electronics | E95: =Raw_Data!E101 -> 2499 | F95: =Raw_Data!F101 -> 1 | G95: =E95*F95 -> 2499 | H95: =PROPER(TRIM(Raw_Data!H101)) -> Vikram Nair | I95: =PROPER(TRIM(Raw_Data!I101)) -> Mumbai | J95: =TRIM(Raw_Data!J101) -> UPI | K95: =PROPER(TRIM(Raw_Data!K101)) -> Delivered | L95: =TEXT(B95,"MMM") -> Sep | M95: =TEXT(B95,"ddd") -> Sun | N95: =IF(K95="Delivered","Delivered",IF(K95="Cancelled","Cancelled","Pending")) -> Delivered | O95: =IF(ROUND(G95-Raw_Data!G101,2)=0,"OK","Corrected") -> OK
A96: =TRIM(Raw_Data!A102) -> AMZ-10109 | B96: =Raw_Data!B102 -> 46271 | C96: =PROPER(TRIM(Raw_Data!C102)) -> Bluetooth Speaker | D96: =TRIM(Raw_Data!D102) -> Electronics | E96: =Raw_Data!E102 -> 1999 | F96: =Raw_Data!F102 -> 1 | G96: =E96*F96 -> 1999 | H96: =PROPER(TRIM(Raw_Data!H102)) -> Aditya Rao | I96: =PROPER(TRIM(Raw_Data!I102)) -> Delhi | J96: =TRIM(Raw_Data!J102) -> UPI | K96: =PROPER(TRIM(Raw_Data!K102)) -> Delivered | L96: =TEXT(B96,"MMM") -> Sep | M96: =TEXT(B96,"ddd") -> Sun | N96: =IF(K96="Delivered","Delivered",IF(K96="Cancelled","Cancelled","Pending")) -> Delivered | O96: =IF(ROUND(G96-Raw_Data!G102,2)=0,"OK","Corrected") -> OK
A97: =TRIM(Raw_Data!A103) -> AMZ-10201 | B97: =Raw_Data!B103 -> 46271 | C97: =PROPER(TRIM(Raw_Data!C103)) -> Mixer Grinder | D97: =TRIM(Raw_Data!D103) -> Home & Kitchen | E97: =Raw_Data!E103 -> 3499 | F97: =Raw_Data!F103 -> 3 | G97: =E97*F97 -> 10497 | H97: =PROPER(TRIM(Raw_Data!H103)) -> Arjun Chopra | I97: =PROPER(TRIM(Raw_Data!I103)) -> Bangalore | J97: =TRIM(Raw_Data!J103) -> Debit Card | K97: =PROPER(TRIM(Raw_Data!K103)) -> Delivered | L97: =TEXT(B97,"MMM") -> Sep | M97: =TEXT(B97,"ddd") -> Sun | N97: =IF(K97="Delivered","Delivered",IF(K97="Cancelled","Cancelled","Pending")) -> Delivered | O97: =IF(ROUND(G97-Raw_Data!G103,2)=0,"OK","Corrected") -> OK
A98: =TRIM(Raw_Data!A104) -> AMZ-10236 | B98: =Raw_Data!B104 -> 46271 | C98: =PROPER(TRIM(Raw_Data!C104)) -> Smart Watch | D98: =TRIM(Raw_Data!D104) -> Electronics | E98: =Raw_Data!E104 -> 4999 | F98: =Raw_Data!F104 -> 1 | G98: =E98*F98 -> 4999 | H98: =PROPER(TRIM(Raw_Data!H104)) -> Arjun Das | I98: =PROPER(TRIM(Raw_Data!I104)) -> Mumbai | J98: =TRIM(Raw_Data!J104) -> Cash On Delivery | K98: =PROPER(TRIM(Raw_Data!K104)) -> Cancelled | L98: =TEXT(B98,"MMM") -> Sep | M98: =TEXT(B98,"ddd") -> Sun | N98: =IF(K98="Delivered","Delivered",IF(K98="Cancelled","Cancelled","Pending")) -> Cancelled | O98: =IF(ROUND(G98-Raw_Data!G104,2)=0,"OK","Corrected") -> OK
A99: =TRIM(Raw_Data!A105) -> AMZ-10266 | B99: =Raw_Data!B105 -> 46271 | C99: =PROPER(TRIM(Raw_Data!C105)) -> Casual Sneakers | D99: =TRIM(Raw_Data!D105) -> Footwear | E99: =Raw_Data!E105 -> 2199 | F99: =Raw_Data!F105 -> 1 | G99: =E99*F99 -> 2199 | H99: =PROPER(TRIM(Raw_Data!H105)) -> Vikram Iyer | I99: =PROPER(TRIM(Raw_Data!I105)) -> Bangalore | J99: =TRIM(Raw_Data!J105) -> Credit Card | K99: =PROPER(TRIM(Raw_Data!K105)) -> Delivered | L99: =TEXT(B99,"MMM") -> Sep | M99: =TEXT(B99,"ddd") -> Sun | N99: =IF(K99="Delivered","Delivered",IF(K99="Cancelled","Cancelled","Pending")) -> Delivered | O99: =IF(ROUND(G99-Raw_Data!G105,2)=0,"OK","Corrected") -> OK
A100: =TRIM(Raw_Data!A106) -> AMZ-10270 | B100: =Raw_Data!B106 -> 46271 | C100: =PROPER(TRIM(Raw_Data!C106)) -> Running Shoes | D100: =TRIM(Raw_Data!D106) -> Footwear | E100: =Raw_Data!E106 -> 3299 | F100: =Raw_Data!F106 -> 2 | G100: =E100*F100 -> 6598 | H100: =PROPER(TRIM(Raw_Data!H106)) -> Sahil Sharma | I100: =PROPER(TRIM(Raw_Data!I106)) -> Ahmedabad | J100: =TRIM(Raw_Data!J106) -> Net Banking | K100: =PROPER(TRIM(Raw_Data!K106)) -> Delivered | L100: =TEXT(B100,"MMM") -> Sep | M100: =TEXT(B100,"ddd") -> Sun | N100: =IF(K100="Delivered","Delivered",IF(K100="Cancelled","Cancelled","Pending")) -> Delivered | O100: =IF(ROUND(G100-Raw_Data!G106,2)=0,"OK","Corrected") -> OK
A101: =TRIM(Raw_Data!A107) -> AMZ-10279 | B101: =Raw_Data!B107 -> 46271 | C101: =PROPER(TRIM(Raw_Data!C107)) -> Air Fryer | D101: =TRIM(Raw_Data!D107) -> Home & Kitchen | E101: =Raw_Data!E107 -> 5999 | F101: =Raw_Data!F107 -> 3 | G101: =E101*F101 -> 17997 | H101: =PROPER(TRIM(Raw_Data!H107)) -> Vikram Nair | I101: =PROPER(TRIM(Raw_Data!I107)) -> Mumbai | J101: =TRIM(Raw_Data!J107) -> Debit Card | K101: =PROPER(TRIM(Raw_Data!K107)) -> Pending | L101: =TEXT(B101,"MMM") -> Sep | M101: =TEXT(B101,"ddd") -> Sun | N101: =IF(K101="Delivered","Delivered",IF(K101="Cancelled","Cancelled","Pending")) -> Pending | O101: =IF(ROUND(G101-Raw_Data!G107,2)=0,"OK","Corrected") -> OK
A102: =TRIM(Raw_Data!A108) -> AMZ-10290 | B102: =Raw_Data!B108 -> 46271 | C102: =PROPER(TRIM(Raw_Data!C108)) -> Bluetooth Speaker | D102: =TRIM(Raw_Data!D108) -> Electronics | E102: =Raw_Data!E108 -> 1999 | F102: =Raw_Data!F108 -> 3 | G102: =E102*F102 -> 5997 | H102: =PROPER(TRIM(Raw_Data!H108)) -> Arjun Chopra | I102: =PROPER(TRIM(Raw_Data!I108)) -> Bangalore | J102: =TRIM(Raw_Data!J108) -> Debit Card | K102: =PROPER(TRIM(Raw_Data!K108)) -> Delivered | L102: =TEXT(B102,"MMM") -> Sep | M102: =TEXT(B102,"ddd") -> Sun | N102: =IF(K102="Delivered","Delivered",IF(K102="Cancelled","Cancelled","Pending")) -> Delivered | O102: =IF(ROUND(G102-Raw_Data!G108,2)=0,"OK","Corrected") -> OK
A103: =TRIM(Raw_Data!A109) -> AMZ-10388 | B103: =Raw_Data!B109 -> 46271 | C103: =PROPER(TRIM(Raw_Data!C109)) -> Bluetooth Speaker | D103: =TRIM(Raw_Data!D109) -> Electronics | E103: =Raw_Data!E109 -> 1999 | F103: =Raw_Data!F109 -> 2 | G103: =E103*F103 -> 3998 | H103: =PROPER(TRIM(Raw_Data!H109)) -> Nikhil Reddy | I103: =PROPER(TRIM(Raw_Data!I109)) -> Chennai | J103: =TRIM(Raw_Data!J109) -> Cash On Delivery | K103: =PROPER(TRIM(Raw_Data!K109)) -> Delivered | L103: =TEXT(B103,"MMM") -> Sep | M103: =TEXT(B103,"ddd") -> Sun | N103: =IF(K103="Delivered","Delivered",IF(K103="Cancelled","Cancelled","Pending")) -> Delivered | O103: =IF(ROUND(G103-Raw_Data!G109,2)=0,"OK","Corrected") -> OK
... A160: =TRIM(Raw_Data!A166) -> AMZ-10336 | B160: =Raw_Data!B166 -> 46275 | C160: =PROPER(TRIM(Raw_Data!C166)) -> Denim Jeans | D160: =TRIM(Raw_Data!D166) -> Clothing | E160: =Raw_Data!E166 -> 1799 | F160: =Raw_Data!F166 -> 4 | G160: =E160*F160 -> 7196 | H160: =PROPER(TRIM(Raw_Data!H166)) -> Vivaan Sharma | I160: =PROPER(TRIM(Raw_Data!I166)) -> Mumbai | J160: =TRIM(Raw_Data!J166) -> Cash On Delivery | K160: =PROPER(TRIM(Raw_Data!K166)) -> Delivered | L160: =TEXT(B160,"MMM") -> Sep | M160: =TEXT(B160,"ddd") -> Thu | N160: =IF(K160="Delivered","Delivered",IF(K160="Cancelled","Cancelled","Pending")) -> Delivered | O160: =IF(ROUND(G160-Raw_Data!G166,2)=0,"OK","Corrected") -> OK
A161: =TRIM(Raw_Data!A168) -> AMZ-10337 | B161: =Raw_Data!B168 -> 46275 | C161: =PROPER(TRIM(Raw_Data!C168)) -> Mixer Grinder | D161: =TRIM(Raw_Data!D168) -> Home & Kitchen | E161: =Raw_Data!E168 -> 3499 | F161: =Raw_Data!F168 -> 1 | G161: =E161*F161 -> 3499 | H161: =PROPER(TRIM(Raw_Data!H168)) -> Meera Mehta | I161: =PROPER(TRIM(Raw_Data!I168)) -> Kolkata | J161: =TRIM(Raw_Data!J168) -> Credit Card | K161: =PROPER(TRIM(Raw_Data!K168)) -> Delivered | L161: =TEXT(B161,"MMM") -> Sep | M161: =TEXT(B161,"ddd") -> Thu | N161: =IF(K161="Delivered","Delivered",IF(K161="Cancelled","Cancelled","Pending")) -> Delivered | O161: =IF(ROUND(G161-Raw_Data!G168,2)=0,"OK","Corrected") -> OK
A162: =TRIM(Raw_Data!A169) -> AMZ-10361 | B162: =Raw_Data!B169 -> 46275 | C162: =PROPER(TRIM(Raw_Data!C169)) -> Bluetooth Speaker | D162: =TRIM(Raw_Data!D169) -> Electronics | E162: =Raw_Data!E169 -> 1999 | F162: =Raw_Data!F169 -> 1 | G162: =E162*F162 -> 1999 | H162: =PROPER(TRIM(Raw_Data!H169)) -> Aarav Joshi | I162: =PROPER(TRIM(Raw_Data!I169)) -> Pune | J162: =TRIM(Raw_Data!J169) -> Credit Card | K162: =PROPER(TRIM(Raw_Data!K169)) -> Delivered | L162: =TEXT(B162,"MMM") -> Sep | M162: =TEXT(B162,"ddd") -> Thu | N162: =IF(K162="Delivered","Delivered",IF(K162="Cancelled","Cancelled","Pending")) -> Delivered | O162: =IF(ROUND(G162-Raw_Data!G169,2)=0,"OK","Corrected") -> OK
A163: =TRIM(Raw_Data!A170) -> AMZ-10369 | B163: =Raw_Data!B170 -> 46275 | C163: =PROPER(TRIM(Raw_Data!C170)) -> Denim Jeans | D163: =TRIM(Raw_Data!D170) -> Clothing | E163: =Raw_Data!E170 -> 1799 | F163: =Raw_Data!F170 -> 1 | G163: =E163*F163 -> 1799 | H163: =PROPER(TRIM(Raw_Data!H170)) -> Neha Patel | I163: =PROPER(TRIM(Raw_Data!I170)) -> Bangalore | J163: =TRIM(Raw_Data!J170) -> UPI | K163: =PROPER(TRIM(Raw_Data!K170)) -> Delivered | L163: =TEXT(B163,"MMM") -> Sep | M163: =TEXT(B163,"ddd") -> Thu | N163: =IF(K163="Delivered","Delivered",IF(K163="Cancelled","Cancelled","Pending")) -> Delivered | O163: =IF(ROUND(G163-Raw_Data!G170,2)=0,"OK","Corrected") -> OK
A164: =TRIM(Raw_Data!A171) -> AMZ-10397 | B164: =Raw_Data!B171 -> 46275 | C164: =PROPER(TRIM(Raw_Data!C171)) -> Mixer Grinder | D164: =TRIM(Raw_Data!D171) -> Home & Kitchen | E164: =Raw_Data!E171 -> 3499 | F164: =Raw_Data!F171 -> 4 | G164: =E164*F164 -> 13996 | H164: =PROPER(TRIM(Raw_Data!H171)) -> Ishaan Chopra | I164: =PROPER(TRIM(Raw_Data!I171)) -> Mumbai | J164: =TRIM(Raw_Data!J171) -> Debit Card | K164: =PROPER(TRIM(Raw_Data!K171)) -> Cancelled | L164: =TEXT(B164,"MMM") -> Sep | M164: =TEXT(B164,"ddd") -> Thu | N164: =IF(K164="Delivered","Delivered",IF(K164="Cancelled","Cancelled","Pending")) -> Cancelled | O164: =IF(ROUND(G164-Raw_Data!G171,2)=0,"OK","Corrected") -> OK
A165: =TRIM(Raw_Data!A172) -> AMZ-10423 | B165: =Raw_Data!B172 -> 46275 | C165: =PROPER(TRIM(Raw_Data!C172)) -> Running Shoes | D165: =TRIM(Raw_Data!D172) -> Footwear | E165: =Raw_Data!E172 -> 3299 | F165: =Raw_Data!F172 -> 4 | G165: =E165*F165 -> 13196 | H165: =PROPER(TRIM(Raw_Data!H172)) -> Kavya Rao | I165: =PROPER(TRIM(Raw_Data!I172)) -> Bangalore | J165: =TRIM(Raw_Data!J172) -> Debit Card | K165: =PROPER(TRIM(Raw_Data!K172)) -> Delivered | L165: =TEXT(B165,"MMM") -> Sep | M165: =TEXT(B165,"ddd") -> Thu | N165: =IF(K165="Delivered","Delivered",IF(K165="Cancelled","Cancelled","Pending")) -> Delivered | O165: =IF(ROUND(G165-Raw_Data!G172,2)=0,"OK","Corrected") -> OK
A166: =TRIM(Raw_Data!A173) -> AMZ-10490 | B166: =Raw_Data!B173 -> 46275 | C166: =PROPER(TRIM(Raw_Data!C173)) -> Mixer Grinder | D166: =TRIM(Raw_Data!D173) -> Home & Kitchen | E166: =Raw_Data!E173 -> 3499 | F166: =Raw_Data!F173 -> 1 | G166: =E166*F166 -> 3499 | H166: =PROPER(TRIM(Raw_Data!H173)) -> Neha Mehta | I166: =PROPER(TRIM(Raw_Data!I173)) -> Lucknow | J166: =TRIM(Raw_Data!J173) -> Debit Card | K166: =PROPER(TRIM(Raw_Data!K173)) -> Cancelled | L166: =TEXT(B166,"MMM") -> Sep | M166: =TEXT(B166,"ddd") -> Thu | N166: =IF(K166="Delivered","Delivered",IF(K166="Cancelled","Cancelled","Pending")) -> Cancelled | O166: =IF(ROUND(G166-Raw_Data!G173,2)=0,"OK","Corrected") -> OK
A167: =TRIM(Raw_Data!A174) -> AMZ-10050 | B167: =Raw_Data!B174 -> 46276 | C167: =PROPER(TRIM(Raw_Data!C174)) -> Power Bank | D167: =TRIM(Raw_Data!D174) -> Electronics | E167: =Raw_Data!E174 -> 1299 | F167: =Raw_Data!F174 -> 1 | G167: =E167*F167 -> 1299 | H167: =PROPER(TRIM(Raw_Data!H174)) -> Neha Patel | I167: =PROPER(TRIM(Raw_Data!I174)) -> Bangalore | J167: =TRIM(Raw_Data!J174) -> Credit Card | K167: =PROPER(TRIM(Raw_Data!K174)) -> Delivered | L167: =TEXT(B167,"MMM") -> Sep | M167: =TEXT(B167,"ddd") -> Fri | N167: =IF(K167="Delivered","Delivered",IF(K167="Cancelled","Cancelled","Pending")) -> Delivered | O167: =IF(ROUND(G167-Raw_Data!G174,2)=0,"OK","Corrected") -> OK
A168: =TRIM(Raw_Data!A175) -> AMZ-10090 | B168: =Raw_Data!B175 -> 46276 | C168: =PROPER(TRIM(Raw_Data!C175)) -> Sandals | D168: =TRIM(Raw_Data!D175) -> Footwear | E168: =Raw_Data!E175 -> 899 | F168: =Raw_Data!F175 -> 2 | G168: =E168*F168 -> 1798 | H168: =PROPER(TRIM(Raw_Data!H175)) -> Neha Kulkarni | I168: =PROPER(TRIM(Raw_Data!I175)) -> Delhi | J168: =TRIM(Raw_Data!J175) -> UPI | K168: =PROPER(TRIM(Raw_Data!K175)) -> Cancelled | L168: =TEXT(B168,"MMM") -> Sep | M168: =TEXT(B168,"ddd") -> Fri | N168: =IF(K168="Delivered","Delivered",IF(K168="Cancelled","Cancelled","Pending")) -> Cancelled | O168: =IF(ROUND(G168-Raw_Data!G175,2)=0,"OK","Corrected") -> OK
A169: =TRIM(Raw_Data!A176) -> AMZ-10120 | B169: =Raw_Data!B176 -> 46276 | C169: =PROPER(TRIM(Raw_Data!C176)) -> Denim Jeans | D169: =TRIM(Raw_Data!D176) -> Clothing | E169: =Raw_Data!E176 -> 1799 | F169: =Raw_Data!F176 -> 1 | G169: =E169*F169 -> 1799 | H169: =PROPER(TRIM(Raw_Data!H176)) -> Neha Patel | I169: =PROPER(TRIM(Raw_Data!I176)) -> Bangalore | J169: =TRIM(Raw_Data!J176) -> UPI | K169: =PROPER(TRIM(Raw_Data!K176)) -> Delivered | L169: =TEXT(B169,"MMM") -> Sep | M169: =TEXT(B169,"ddd") -> Fri | N169: =IF(K169="Delivered","Delivered",IF(K169="Cancelled","Cancelled","Pending")) -> Delivered | O169: =IF(ROUND(G169-Raw_Data!G176,2)=0,"OK","Corrected") -> OK
A170: =TRIM(Raw_Data!A177) -> AMZ-10122 | B170: =Raw_Data!B177 -> 46276 | C170: =PROPER(TRIM(Raw_Data!C177)) -> Python Programming Book | D170: =TRIM(Raw_Data!D177) -> Books | E170: =Raw_Data!E177 -> 699 | F170: =Raw_Data!F177 -> 1 | G170: =E170*F170 -> 699 | H170: =PROPER(TRIM(Raw_Data!H177)) -> Aditya Sharma | I170: =PROPER(TRIM(Raw_Data!I177)) -> Ahmedabad | J170: =TRIM(Raw_Data!J177) -> UPI | K170: =PROPER(TRIM(Raw_Data!K177)) -> Delivered | L170: =TEXT(B170,"MMM") -> Sep | M170: =TEXT(B170,"ddd") -> Fri | N170: =IF(K170="Delivered","Delivered",IF(K170="Cancelled","Cancelled","Pending")) -> Delivered | O170: =IF(ROUND(G170-Raw_Data!G177,2)=0,"OK","Corrected") -> OK
A171: =TRIM(Raw_Data!A178) -> AMZ-10140 | B171: =Raw_Data!B178 -> 46276 | C171: =PROPER(TRIM(Raw_Data!C178)) -> Wireless Earbuds | D171: =TRIM(Raw_Data!D178) -> Electronics | E171: =Raw_Data!E178 -> 2499 | F171: =Raw_Data!F178 -> 2 | G171: =E171*F171 -> 4998 | H171: =PROPER(TRIM(Raw_Data!H178)) -> Ishaan Singh | I171: =PROPER(TRIM(Raw_Data!I178)) -> Delhi | J171: =TRIM(Raw_Data!J178) -> Debit Card | K171: =PROPER(TRIM(Raw_Data!K178)) -> Delivered | L171: =TEXT(B171,"MMM") -> Sep | M171: =TEXT(B171,"ddd") -> Fri | N171: =IF(K171="Delivered","Delivered",IF(K171="Cancelled","Cancelled","Pending")) -> Delivered | O171: =IF(ROUND(G171-Raw_Data!G178,2)=0,"OK","Corrected") -> OK
A172: =TRIM(Raw_Data!A179) -> AMZ-10191 | B172: =Raw_Data!B179 -> 46276 | C172: =PROPER(TRIM(Raw_Data!C179)) -> Wireless Earbuds | D172: =TRIM(Raw_Data!D179) -> Electronics | E172: =Raw_Data!E179 -> 2499 | F172: =Raw_Data!F179 -> 4 | G172: =E172*F172 -> 9996 | H172: =PROPER(TRIM(Raw_Data!H179)) -> Priya Das | I172: =PROPER(TRIM(Raw_Data!I179)) -> Hyderabad | J172: =TRIM(Raw_Data!J179) -> Debit Card | K172: =PROPER(TRIM(Raw_Data!K179)) -> Delivered | L172: =TEXT(B172,"MMM") -> Sep | M172: =TEXT(B172,"ddd") -> Fri | N172: =IF(K172="Delivered","Delivered",IF(K172="Cancelled","Cancelled","Pending")) -> Delivered | O172: =IF(ROUND(G172-Raw_Data!G179,2)=0,"OK","Corrected") -> OK
... A179: =TRIM(Raw_Data!A186) -> AMZ-10368 | B179: =Raw_Data!B186 -> 46276 | C179: =PROPER(TRIM(Raw_Data!C186)) -> Mixer Grinder | D179: =TRIM(Raw_Data!D186) -> Home & Kitchen | E179: =Raw_Data!E186 -> 3499 | F179: =Raw_Data!F186 -> 2 | G179: =E179*F179 -> 6998 | H179: =PROPER(TRIM(Raw_Data!H186)) -> Vikram Iyer | I179: =PROPER(TRIM(Raw_Data!I186)) -> Bangalore | J179: =TRIM(Raw_Data!J186) -> UPI | K179: =PROPER(TRIM(Raw_Data!K186)) -> Pending | L179: =TEXT(B179,"MMM") -> Sep | M179: =TEXT(B179,"ddd") -> Fri | N179: =IF(K179="Delivered","Delivered",IF(K179="Cancelled","Cancelled","Pending")) -> Pending | O179: =IF(ROUND(G179-Raw_Data!G186,2)=0,"OK","Corrected") -> OK
A180: =TRIM(Raw_Data!A188) -> AMZ-10378 | B180: =Raw_Data!B188 -> 46276 | C180: =PROPER(TRIM(Raw_Data!C188)) -> Bluetooth Speaker | D180: =TRIM(Raw_Data!D188) -> Electronics | E180: =Raw_Data!E188 -> 1999 | F180: =Raw_Data!F188 -> 1 | G180: =E180*F180 -> 1999 | H180: =PROPER(TRIM(Raw_Data!H188)) -> Vivaan Joshi | I180: =PROPER(TRIM(Raw_Data!I188)) -> Pune | J180: =TRIM(Raw_Data!J188) -> UPI | K180: =PROPER(TRIM(Raw_Data!K188)) -> Pending | L180: =TEXT(B180,"MMM") -> Sep | M180: =TEXT(B180,"ddd") -> Fri | N180: =IF(K180="Delivered","Delivered",IF(K180="Cancelled","Cancelled","Pending")) -> Pending | O180: =IF(ROUND(G180-Raw_Data!G188,2)=0,"OK","Corrected") -> OK
A181: =TRIM(Raw_Data!A189) -> AMZ-10385 | B181: =Raw_Data!B189 -> 46276 | C181: =PROPER(TRIM(Raw_Data!C189)) -> Python Programming Book | D181: =TRIM(Raw_Data!D189) -> Books | E181: =Raw_Data!E189 -> 699 | F181: =Raw_Data!F189 -> 1 | G181: =E181*F181 -> 699 | H181: =PROPER(TRIM(Raw_Data!H189)) -> Arjun Verma | I181: =PROPER(TRIM(Raw_Data!I189)) -> Pune | J181: =TRIM(Raw_Data!J189) -> UPI | K181: =PROPER(TRIM(Raw_Data!K189)) -> Delivered | L181: =TEXT(B181,"MMM") -> Sep | M181: =TEXT(B181,"ddd") -> Fri | N181: =IF(K181="Delivered","Delivered",IF(K181="Cancelled","Cancelled","Pending")) -> Delivered | O181: =IF(ROUND(G181-Raw_Data!G189,2)=0,"OK","Corrected") -> OK
A182: =TRIM(Raw_Data!A190) -> AMZ-10386 | B182: =Raw_Data!B190 -> 46276 | C182: =PROPER(TRIM(Raw_Data!C190)) -> Power Bank | D182: =TRIM(Raw_Data!D190) -> Electronics | E182: =Raw_Data!E190 -> 1299 | F182: =Raw_Data!F190 -> 1 | G182: =E182*F182 -> 1299 | H182: =PROPER(TRIM(Raw_Data!H190)) -> Sahil Sharma | I182: =PROPER(TRIM(Raw_Data!I190)) -> Ahmedabad | J182: =TRIM(Raw_Data!J190) -> UPI | K182: =PROPER(TRIM(Raw_Data!K190)) -> Cancelled | L182: =TEXT(B182,"MMM") -> Sep | M182: =TEXT(B182,"ddd") -> Fri | N182: =IF(K182="Delivered","Delivered",IF(K182="Cancelled","Cancelled","Pending")) -> Cancelled | O182: =IF(ROUND(G182-Raw_Data!G190,2)=0,"OK","Corrected") -> OK
A183: =TRIM(Raw_Data!A191) -> AMZ-10403 | B183: =Raw_Data!B191 -> 46276 | C183: =PROPER(TRIM(Raw_Data!C191)) -> Water Bottle | D183: =TRIM(Raw_Data!D191) -> Home & Kitchen | E183: =Raw_Data!E191 -> 499 | F183: =Raw_Data!F191 -> 1 | G183: =E183*F183 -> 499 | H183: =PROPER(TRIM(Raw_Data!H191)) -> Vikram Nair | I183: =PROPER(TRIM(Raw_Data!I191)) -> Mumbai | J183: =TRIM(Raw_Data!J191) -> UPI | K183: =PROPER(TRIM(Raw_Data!K191)) -> Delivered | L183: =TEXT(B183,"MMM") -> Sep | M183: =TEXT(B183,"ddd") -> Fri | N183: =IF(K183="Delivered","Delivered",IF(K183="Cancelled","Cancelled","Pending")) -> Delivered | O183: =IF(ROUND(G183-Raw_Data!G191,2)=0,"OK","Corrected") -> OK
A184: =TRIM(Raw_Data!A192) -> AMZ-10445 | B184: =Raw_Data!B192 -> 46276 | C184: =PROPER(TRIM(Raw_Data!C192)) -> Self Help Book | D184: =TRIM(Raw_Data!D192) -> Books | E184: =Raw_Data!E192 -> 399 | F184: =Raw_Data!F192 -> 1 | G184: =E184*F184 -> 399 | H184: =PROPER(TRIM(Raw_Data!H192)) -> Meera Singh | I184: =PROPER(TRIM(Raw_Data!I192)) -> Hyderabad | J184: =TRIM(Raw_Data!J192) -> UPI | K184: =PROPER(TRIM(Raw_Data!K192)) -> Delivered | L184: =TEXT(B184,"MMM") -> Sep | M184: =TEXT(B184,"ddd") -> Fri | N184: =IF(K184="Delivered","Delivered",IF(K184="Cancelled","Cancelled","Pending")) -> Delivered | O184: =IF(ROUND(G184-Raw_Data!G192,2)=0,"OK","Corrected") -> OK
A185: =TRIM(Raw_Data!A193) -> AMZ-10446 | B185: =Raw_Data!B193 -> 46276 | C185: =PROPER(TRIM(Raw_Data!C193)) -> Water Bottle | D185: =TRIM(Raw_Data!D193) -> Home & Kitchen | E185: =Raw_Data!E193 -> 499 | F185: =Raw_Data!F193 -> 1 | G185: =E185*F185 -> 499 | H185: =PROPER(TRIM(Raw_Data!H193)) -> Priya Reddy | I185: =PROPER(TRIM(Raw_Data!I193)) -> Mumbai | J185: =TRIM(Raw_Data!J193) -> Credit Card | K185: =PROPER(TRIM(Raw_Data!K193)) -> Delivered | L185: =TEXT(B185,"MMM") -> Sep | M185: =TEXT(B185,"ddd") -> Fri | N185: =IF(K185="Delivered","Delivered",IF(K185="Cancelled","Cancelled","Pending")) -> Delivered | O185: =IF(ROUND(G185-Raw_Data!G193,2)=0,"OK","Corrected") -> OK
A186: =TRIM(Raw_Data!A194) -> AMZ-10470 | B186: =Raw_Data!B194 -> 46276 | C186: =PROPER(TRIM(Raw_Data!C194)) -> Denim Jeans | D186: =TRIM(Raw_Data!D194) -> Clothing | E186: =Raw_Data!E194 -> 1799 | F186: =Raw_Data!F194 -> 1 | G186: =E186*F186 -> 1799 | H186: =PROPER(TRIM(Raw_Data!H194)) -> Nikhil Reddy | I186: =PROPER(TRIM(Raw_Data!I194)) -> Chennai | J186: =TRIM(Raw_Data!J194) -> Credit Card | K186: =PROPER(TRIM(Raw_Data!K194)) -> Cancelled | L186: =TEXT(B186,"MMM") -> Sep | M186: =TEXT(B186,"ddd") -> Fri | N186: =IF(K186="Delivered","Delivered",IF(K186="Cancelled","Cancelled","Pending")) -> Cancelled | O186: =IF(ROUND(G186-Raw_Data!G194,2)=0,"OK","Corrected") -> OK
A187: =TRIM(Raw_Data!A195) -> AMZ-10487 | B187: =Raw_Data!B195 -> 46276 | C187: =PROPER(TRIM(Raw_Data!C195)) -> Python Programming Book | D187: =TRIM(Raw_Data!D195) -> Books | E187: =Raw_Data!E195 -> 699 | F187: =Raw_Data!F195 -> 1 | G187: =E187*F187 -> 699 | H187: =PROPER(TRIM(Raw_Data!H195)) -> Nikhil Joshi | I187: =PROPER(TRIM(Raw_Data!I195)) -> Lucknow | J187: =TRIM(Raw_Data!J195) -> Cash On Delivery | K187: =PROPER(TRIM(Raw_Data!K195)) -> Delivered | L187: =TEXT(B187,"MMM") -> Sep | M187: =TEXT(B187,"ddd") -> Fri | N187: =IF(K187="Delivered","Delivered",IF(K187="Cancelled","Cancelled","Pending")) -> Delivered | O187: =IF(ROUND(G187-Raw_Data!G195,2)=0,"OK","Corrected") -> OK
A188: =TRIM(Raw_Data!A196) -> AMZ-10172 | B188: =Raw_Data!B196 -> 46277 | C188: =PROPER(TRIM(Raw_Data!C196)) -> Water Bottle | D188: =TRIM(Raw_Data!D196) -> Home & Kitchen | E188: =Raw_Data!E196 -> 499 | F188: =Raw_Data!F196 -> 1 | G188: =E188*F188 -> 499 | H188: =PROPER(TRIM(Raw_Data!H196)) -> Rajesh Reddy | I188: =PROPER(TRIM(Raw_Data!I196)) -> Delhi | J188: =TRIM(Raw_Data!J196) -> UPI | K188: =PROPER(TRIM(Raw_Data!K196)) -> Delivered | L188: =TEXT(B188,"MMM") -> Sep | M188: =TEXT(B188,"ddd") -> Sat | N188: =IF(K188="Delivered","Delivered",IF(K188="Cancelled","Cancelled","Pending")) -> Delivered | O188: =IF(ROUND(G188-Raw_Data!G196,2)=0,"OK","Corrected") -> OK
A189: =TRIM(Raw_Data!A197) -> AMZ-10178 | B189: =Raw_Data!B197 -> 46277 | C189: =PROPER(TRIM(Raw_Data!C197)) -> Water Bottle | D189: =TRIM(Raw_Data!D197) -> Home & Kitchen | E189: =Raw_Data!E197 -> 499 | F189: =Raw_Data!F197 -> 1 | G189: =E189*F189 -> 499 | H189: =PROPER(TRIM(Raw_Data!H197)) -> Aarav Das | I189: =PROPER(TRIM(Raw_Data!I197)) -> Jaipur | J189: =TRIM(Raw_Data!J197) -> Cash On Delivery | K189: =PROPER(TRIM(Raw_Data!K197)) -> Delivered | L189: =TEXT(B189,"MMM") -> Sep | M189: =TEXT(B189,"ddd") -> Sat | N189: =IF(K189="Delivered","Delivered",IF(K189="Cancelled","Cancelled","Pending")) -> Delivered | O189: =IF(ROUND(G189-Raw_Data!G197,2)=0,"OK","Corrected") -> OK
A190: =TRIM(Raw_Data!A198) -> AMZ-10180 | B190: =Raw_Data!B198 -> 46277 | C190: =PROPER(TRIM(Raw_Data!C198)) -> Python Programming Book | D190: =TRIM(Raw_Data!D198) -> Books | E190: =Raw_Data!E198 -> 699 | F190: =Raw_Data!F198 -> 1 | G190: =E190*F190 -> 699 | H190: =PROPER(TRIM(Raw_Data!H198)) -> Tanvi Iyer | I190: =PROPER(TRIM(Raw_Data!I198)) -> Kolkata | J190: =TRIM(Raw_Data!J198) -> Credit Card | K190: =PROPER(TRIM(Raw_Data!K198)) -> Delivered | L190: =TEXT(B190,"MMM") -> Sep | M190: =TEXT(B190,"ddd") -> Sat | N190: =IF(K190="Delivered","Delivered",IF(K190="Cancelled","Cancelled","Pending")) -> Delivered | O190: =IF(ROUND(G190-Raw_Data!G198,2)=0,"OK","Corrected") -> OK
A191: =TRIM(Raw_Data!A199) -> AMZ-10246 | B191: =Raw_Data!B199 -> 46277 | C191: =PROPER(TRIM(Raw_Data!C199)) -> Running Shoes | D191: =TRIM(Raw_Data!D199) -> Footwear | E191: =Raw_Data!E199 -> 3299 | F191: =Raw_Data!F199 -> 1 | G191: =E191*F191 -> 3299 | H191: =PROPER(TRIM(Raw_Data!H199)) -> Aditya Sharma | I191: =PROPER(TRIM(Raw_Data!I199)) -> Ahmedabad | J191: =TRIM(Raw_Data!J199) -> UPI | K191: =PROPER(TRIM(Raw_Data!K199)) -> Delivered | L191: =TEXT(B191,"MMM") -> Sep | M191: =TEXT(B191,"ddd") -> Sat | N191: =IF(K191="Delivered","Delivered",IF(K191="Cancelled","Cancelled","Pending")) -> Delivered | O191: =IF(ROUND(G191-Raw_Data!G199,2)=0,"OK","Corrected") -> OK
... A256: =TRIM(Raw_Data!A264) -> AMZ-10148 | B256: =Raw_Data!B264 -> 46280 | C256: =PROPER(TRIM(Raw_Data!C264)) -> Smart Watch | D256: =TRIM(Raw_Data!D264) -> Electronics | E256: =Raw_Data!E264 -> 4999 | F256: =Raw_Data!F264 -> 1 | G256: =E256*F256 -> 4999 | H256: =PROPER(TRIM(Raw_Data!H264)) -> Ishaan Singh | I256: =PROPER(TRIM(Raw_Data!I264)) -> Delhi | J256: =TRIM(Raw_Data!J264) -> UPI | K256: =PROPER(TRIM(Raw_Data!K264)) -> Delivered | L256: =TEXT(B256,"MMM") -> Sep | M256: =TEXT(B256,"ddd") -> Tue | N256: =IF(K256="Delivered","Delivered",IF(K256="Cancelled","Cancelled","Pending")) -> Delivered | O256: =IF(ROUND(G256-Raw_Data!G264,2)=0,"OK","Corrected") -> OK
A257: =TRIM(Raw_Data!A266) -> AMZ-10157 | B257: =Raw_Data!B266 -> 46280 | C257: =PROPER(TRIM(Raw_Data!C266)) -> Water Bottle | D257: =TRIM(Raw_Data!D266) -> Home & Kitchen | E257: =Raw_Data!E266 -> 499 | F257: =Raw_Data!F266 -> 1 | G257: =E257*F257 -> 499 | H257: =PROPER(TRIM(Raw_Data!H266)) -> Tanvi Joshi | I257: =PROPER(TRIM(Raw_Data!I266)) -> Bangalore | J257: =TRIM(Raw_Data!J266) -> UPI | K257: =PROPER(TRIM(Raw_Data!K266)) -> Delivered | L257: =TEXT(B257,"MMM") -> Sep | M257: =TEXT(B257,"ddd") -> Tue | N257: =IF(K257="Delivered","Delivered",IF(K257="Cancelled","Cancelled","Pending")) -> Delivered | O257: =IF(ROUND(G257-Raw_Data!G266,2)=0,"OK","Corrected") -> OK
A258: =TRIM(Raw_Data!A267) -> AMZ-10168 | B258: =Raw_Data!B267 -> 46280 | C258: =PROPER(TRIM(Raw_Data!C267)) -> Power Bank | D258: =TRIM(Raw_Data!D267) -> Electronics | E258: =Raw_Data!E267 -> 1299 | F258: =Raw_Data!F267 -> 1 | G258: =E258*F258 -> 1299 | H258: =PROPER(TRIM(Raw_Data!H267)) -> Neha Kulkarni | I258: =PROPER(TRIM(Raw_Data!I267)) -> Delhi | J258: =TRIM(Raw_Data!J267) -> UPI | K258: =PROPER(TRIM(Raw_Data!K267)) -> Shipped | L258: =TEXT(B258,"MMM") -> Sep | M258: =TEXT(B258,"ddd") -> Tue | N258: =IF(K258="Delivered","Delivered",IF(K258="Cancelled","Cancelled","Pending")) -> Pending | O258: =IF(ROUND(G258-Raw_Data!G267,2)=0,"OK","Corrected") -> OK
A259: =TRIM(Raw_Data!A268) -> AMZ-10173 | B259: =Raw_Data!B268 -> 46280 | C259: =PROPER(TRIM(Raw_Data!C268)) -> Denim Jeans | D259: =TRIM(Raw_Data!D268) -> Clothing | E259: =Raw_Data!E268 -> 1799 | F259: =Raw_Data!F268 -> 3 | G259: =E259*F259 -> 5397 | H259: =PROPER(TRIM(Raw_Data!H268)) -> Vikram Iyer | I259: =PROPER(TRIM(Raw_Data!I268)) -> Bangalore | J259: =TRIM(Raw_Data!J268) -> UPI | K259: =PROPER(TRIM(Raw_Data!K268)) -> Delivered | L259: =TEXT(B259,"MMM") -> Sep | M259: =TEXT(B259,"ddd") -> Tue | N259: =IF(K259="Delivered","Delivered",IF(K259="Cancelled","Cancelled","Pending")) -> Delivered | O259: =IF(ROUND(G259-Raw_Data!G268,2)=0,"OK","Corrected") -> OK
A260: =TRIM(Raw_Data!A269) -> AMZ-10187 | B260: =Raw_Data!B269 -> 46280 | C260: =PROPER(TRIM(Raw_Data!C269)) -> Air Fryer | D260: =TRIM(Raw_Data!D269) -> Home & Kitchen | E260: =Raw_Data!E269 -> 5999 | F260: =Raw_Data!F269 -> 3 | G260: =E260*F260 -> 17997 | H260: =PROPER(TRIM(Raw_Data!H269)) -> Nikhil Joshi | I260: =PROPER(TRIM(Raw_Data!I269)) -> Lucknow | J260: =TRIM(Raw_Data!J269) -> Cash On Delivery | K260: =PROPER(TRIM(Raw_Data!K269)) -> Delivered | L260: =TEXT(B260,"MMM") -> Sep | M260: =TEXT(B260,"ddd") -> Tue | N260: =IF(K260="Delivered","Delivered",IF(K260="Cancelled","Cancelled","Pending")) -> Delivered | O260: =IF(ROUND(G260-Raw_Data!G269,2)=0,"OK","Corrected") -> OK
A261: =TRIM(Raw_Data!A270) -> AMZ-10208 | B261: =Raw_Data!B270 -> 46280 | C261: =PROPER(TRIM(Raw_Data!C270)) -> Cotton T-Shirt | D261: =TRIM(Raw_Data!D270) -> Clothing | E261: =Raw_Data!E270 -> 599 | F261: =Raw_Data!F270 -> 1 | G261: =E261*F261 -> 599 | H261: =PROPER(TRIM(Raw_Data!H270)) -> Aarav Joshi | I261: =PROPER(TRIM(Raw_Data!I270)) -> Pune | J261: =TRIM(Raw_Data!J270) -> Net Banking | K261: =PROPER(TRIM(Raw_Data!K270)) -> Cancelled | L261: =TEXT(B261,"MMM") -> Sep | M261: =TEXT(B261,"ddd") -> Tue | N261: =IF(K261="Delivered","Delivered",IF(K261="Cancelled","Cancelled","Pending")) -> Cancelled | O261: =IF(ROUND(G261-Raw_Data!G270,2)=0,"OK","Corrected") -> OK
A262: =TRIM(Raw_Data!A271) -> AMZ-10221 | B262: =Raw_Data!B271 -> 46280 | C262: =PROPER(TRIM(Raw_Data!C271)) -> Wireless Earbuds | D262: =TRIM(Raw_Data!D271) -> Electronics | E262: =Raw_Data!E271 -> 2499 | F262: =Raw_Data!F271 -> 1 | G262: =E262*F262 -> 2499 | H262: =PROPER(TRIM(Raw_Data!H271)) -> Neha Kulkarni | I262: =PROPER(TRIM(Raw_Data!I271)) -> Delhi | J262: =TRIM(Raw_Data!J271) -> Credit Card | K262: =PROPER(TRIM(Raw_Data!K271)) -> Shipped | L262: =TEXT(B262,"MMM") -> Sep | M262: =TEXT(B262,"ddd") -> Tue | N262: =IF(K262="Delivered","Delivered",IF(K262="Cancelled","Cancelled","Pending")) -> Pending | O262: =IF(ROUND(G262-Raw_Data!G271,2)=0,"OK","Corrected") -> OK
A263: =TRIM(Raw_Data!A272) -> AMZ-10223 | B263: =Raw_Data!B272 -> 46280 | C263: =PROPER(TRIM(Raw_Data!C272)) -> Mixer Grinder | D263: =TRIM(Raw_Data!D272) -> Home & Kitchen | E263: =Raw_Data!E272 -> 3499 | F263: =Raw_Data!F272 -> 1 | G263: =E263*F263 -> 3499 | H263: =PROPER(TRIM(Raw_Data!H272)) -> Aditya Kulkarni | I263: =PROPER(TRIM(Raw_Data!I272)) -> Bangalore | J263: =TRIM(Raw_Data!J272) -> UPI | K263: =PROPER(TRIM(Raw_Data!K272)) -> Pending | L263: =TEXT(B263,"MMM") -> Sep | M263: =TEXT(B263,"ddd") -> Tue | N263: =IF(K263="Delivered","Delivered",IF(K263="Cancelled","Cancelled","Pending")) -> Pending | O263: =IF(ROUND(G263-Raw_Data!G272,2)=0,"OK","Corrected") -> OK
A264: =TRIM(Raw_Data!A273) -> AMZ-10240 | B264: =Raw_Data!B273 -> 46280 | C264: =PROPER(TRIM(Raw_Data!C273)) -> Running Shoes | D264: =TRIM(Raw_Data!D273) -> Footwear | E264: =Raw_Data!E273 -> 3299 | F264: =Raw_Data!F273 -> 3 | G264: =E264*F264 -> 9897 | H264: =PROPER(TRIM(Raw_Data!H273)) -> Nikhil Kulkarni | I264: =PROPER(TRIM(Raw_Data!I273)) -> Pune | J264: =TRIM(Raw_Data!J273) -> Debit Card | K264: =PROPER(TRIM(Raw_Data!K273)) -> Cancelled | L264: =TEXT(B264,"MMM") -> Sep | M264: =TEXT(B264,"ddd") -> Tue | N264: =IF(K264="Delivered","Delivered",IF(K264="Cancelled","Cancelled","Pending")) -> Cancelled | O264: =IF(ROUND(G264-Raw_Data!G273,2)=0,"OK","Corrected") -> OK
A265: =TRIM(Raw_Data!A274) -> AMZ-10267 | B265: =Raw_Data!B274 -> 46280 | C265: =PROPER(TRIM(Raw_Data!C274)) -> Wireless Earbuds | D265: =TRIM(Raw_Data!D274) -> Electronics | E265: =Raw_Data!E274 -> 2499 | F265: =Raw_Data!F274 -> 2 | G265: =E265*F265 -> 4998 | H265: =PROPER(TRIM(Raw_Data!H274)) -> Kavya Patel | I265: =PROPER(TRIM(Raw_Data!I274)) -> Hyderabad | J265: =TRIM(Raw_Data!J274) -> Debit Card | K265: =PROPER(TRIM(Raw_Data!K274)) -> Delivered | L265: =TEXT(B265,"MMM") -> Sep | M265: =TEXT(B265,"ddd") -> Tue | N265: =IF(K265="Delivered","Delivered",IF(K265="Cancelled","Cancelled","Pending")) -> Delivered | O265: =IF(ROUND(G265-Raw_Data!G274,2)=0,"OK","Corrected") -> OK
A266: =TRIM(Raw_Data!A275) -> AMZ-10339 | B266: =Raw_Data!B275 -> 46280 | C266: =PROPER(TRIM(Raw_Data!C275)) -> Self Help Book | D266: =TRIM(Raw_Data!D275) -> Books | E266: =Raw_Data!E275 -> 399 | F266: =Raw_Data!F275 -> 1 | G266: =E266*F266 -> 399 | H266: =PROPER(TRIM(Raw_Data!H275)) -> Suresh Das | I266: =PROPER(TRIM(Raw_Data!I275)) -> Bangalore | J266: =TRIM(Raw_Data!J275) -> Debit Card | K266: =PROPER(TRIM(Raw_Data!K275)) -> Delivered | L266: =TEXT(B266,"MMM") -> Sep | M266: =TEXT(B266,"ddd") -> Tue | N266: =IF(K266="Delivered","Delivered",IF(K266="Cancelled","Cancelled","Pending")) -> Delivered | O266: =IF(ROUND(G266-Raw_Data!G275,2)=0,"OK","Corrected") -> Corrected
A267: =TRIM(Raw_Data!A276) -> AMZ-10387 | B267: =Raw_Data!B276 -> 46280 | C267: =PROPER(TRIM(Raw_Data!C276)) -> Denim Jeans | D267: =TRIM(Raw_Data!D276) -> Clothing | E267: =Raw_Data!E276 -> 1799 | F267: =Raw_Data!F276 -> 2 | G267: =E267*F267 -> 3598 | H267: =PROPER(TRIM(Raw_Data!H276)) -> Nikhil Reddy | I267: =PROPER(TRIM(Raw_Data!I276)) -> Chennai | J267: =TRIM(Raw_Data!J276) -> UPI | K267: =PROPER(TRIM(Raw_Data!K276)) -> Cancelled | L267: =TEXT(B267,"MMM") -> Sep | M267: =TEXT(B267,"ddd") -> Tue | N267: =IF(K267="Delivered","Delivered",IF(K267="Cancelled","Cancelled","Pending")) -> Cancelled | O267: =IF(ROUND(G267-Raw_Data!G276,2)=0,"OK","Corrected") -> OK
A268: =TRIM(Raw_Data!A277) -> AMZ-10391 | B268: =Raw_Data!B277 -> 46280 | C268: =PROPER(TRIM(Raw_Data!C277)) -> Python Programming Book | D268: =TRIM(Raw_Data!D277) -> Books | E268: =Raw_Data!E277 -> 699 | F268: =Raw_Data!F277 -> 1 | G268: =E268*F268 -> 699 | H268: =PROPER(TRIM(Raw_Data!H277)) -> Pooja Gupta | I268: =PROPER(TRIM(Raw_Data!I277)) -> Bangalore | J268: =TRIM(Raw_Data!J277) -> UPI | K268: =PROPER(TRIM(Raw_Data!K277)) -> Delivered | L268: =TEXT(B268,"MMM") -> Sep | M268: =TEXT(B268,"ddd") -> Tue | N268: =IF(K268="Delivered","Delivered",IF(K268="Cancelled","Cancelled","Pending")) -> Delivered | O268: =IF(ROUND(G268-Raw_Data!G277,2)=0,"OK","Corrected") -> OK
...

Sheet Raw_Data
A1: Order ID | B1: Date | C1: Product | D1: Category | E1: Price | F1: Quantity | G1: Total Sales | H1: Customer Name | I1: Customer Location | J1: Payment Method | K1: Order Status
A2: AMZ-10052 | B2: 46266 | C2: mixer grinder | D2: Home & Kitchen | E2: 3499 | F2: 1 | G2: 3499 | H2: Vikram Joshi | I2: Hyderabad | J2: UPI | K2: Delivered
A3: AMZ-10123 | B3: 46266 | C3: SELF HELP BOOK | D3: Books | E3: 399 | F3: 3 | G3: 1197 | H3: Vikram Iyer | I3: Bangalore | J3: Debit Card | K3: Delivered
A4: AMZ-10196 | B4: 46266 | C4: Water Bottle | D4: Home & Kitchen | E4: 499 | F4: 2 | G4: 998 | H4: Priya Das | I4: Hyderabad | J4: Debit Card | K4: Delivered
A5: AMZ-10245 | B5: 46266 | C5: Self Help Book | D5: Books | E5: 399 | F5: 3 | G5: 1197 | H5: Vivaan Sharma | I5: Mumbai | J5: Credit Card | K5: Delivered
A6: AMZ-10252 | B6: 46266 | C6: Cotton T-Shirt | D6: Clothing | E6: 599 | F6: 1 | G6: 599 | H6: Priya Chopra | I6: bangalore | J6: Debit Card | K6: Delivered
A7: AMZ-10255 | B7: 46266 | C7: Sandals | D7: Footwear | E7: 899 | F7: 4 | G7: 3596 | H7: Priya Das | I7: HYDERABAD | J7: Credit Card | K7: Delivered
A8: AMZ-10255 | B8: 46266 | C8: Sandals | D8: Footwear | E8: 899 | F8: 4 | G8: 3596 | H8: Priya Das | I8: HYDERABAD | J8: Credit Card | K8: Delivered
A9: AMZ-10301 | B9: 46266 | C9: Sandals | D9: Footwear | E9: 899 | F9: 3 | G9: 2697 | H9: Nikhil Reddy | I9: Chennai | J9: UPI | K9: Delivered
A10: AMZ-10301 | B10: 46266 | C10: Sandals | D10: Footwear | E10: 899 | F10: 3 | G10: 2697 | H10: Nikhil Reddy | I10: Chennai | J10: UPI | K10: Delivered
A11: AMZ-10364 | B11: 46266 | C11: Water Bottle | D11: Home & Kitchen | E11: 499 | F11: 3 | G11: 1497 | H11: VIVAAN DAS | I11: Ahmedabad | J11: UPI | K11: Delivered
A12: AMZ-10414 | B12: 46266 | C12: Air Fryer | D12: Home & Kitchen | E12: 5999 | F12: 1 | G12: 5999 | H12: Aditya Singh | I12: Delhi | J12: UPI | K12: Delivered
A13: AMZ-10484 | B13: 46266 | C13: Water Bottle | D13: Home & Kitchen | E13: 499 | F13: 1 | G13: 499 | H13: Priya Iyer | I13: Delhi | J13: Debit Card | K13: Delivered
... A516: AMZ-10476 | B516: 46295 | C516: Denim Jeans | D516: Clothing | E516: 1799 | F516: 1 | G516: 1799 | H516: Sneha Reddy | I516: Pune | J516: UPI | K516: Delivered

Sheet Insights
B1: Insights & Recommendations
B2: Computed from ALL data (not affected by Dashboard filters). Text updates automatically if the data changes.
B4: Question | C4: Finding
B5: Highest-selling product | C5: =INDEX(Pivots!$A$21:$A$34,MATCH(MAX(Pivots!$F$21:$F$34),Pivots!$F$21:$F$34,0))&" (₹"&TEXT(MAX(Pivots!$F$21:$F$34),"#,##0")&")"&" – "&TEXT(MAX(Pivots!$F$21:$F$34)/Pivots!$F$35,"0.0%")&" of total sales" -> Smart Watch (₹2,34,953) – 15.0% of total sales
B6: Lowest-selling product | C6: =INDEX(Pivots!$A$21:$A$34,MATCH(MIN(Pivots!$F$21:$F$34),Pivots!$F$21:$F$34,0))&" (₹"&TEXT(MIN(Pivots!$F$21:$F$34),"#,##0")&")" -> Self Help Book (₹27,531)
B7: Best category | C7: =INDEX(Pivots!$A$11:$A$15,MATCH(MAX(Pivots!$F$11:$F$15),Pivots!$F$11:$F$15,0))&" (₹"&TEXT(MAX(Pivots!$F$11:$F$15),"#,##0")&")"&" – "&TEXT(MAX(Pivots!$F$11:$F$15)/Pivots!$F$16,"0.0%")&" of total sales" -> Electronics (₹5,95,070) – 38.0% of total sales
B8: Weakest category | C8: =INDEX(Pivots!$A$11:$A$15,MATCH(MIN(Pivots!$F$11:$F$15),Pivots!$F$11:$F$15,0))&" (₹"&TEXT(MIN(Pivots!$F$11:$F$15),"#,##0")&")"&" – "&TEXT(MIN(Pivots!$F$11:$F$15)/Pivots!$F$16,"0.0%")&" of total sales" -> Books (₹60,384) – 3.9% of total sales
B9: Strongest city | C9: =INDEX(Pivots!$A$40:$A$49,MATCH(MAX(Pivots!$F$40:$F$49),Pivots!$F$40:$F$49,0))&" (₹"&TEXT(MAX(Pivots!$F$40:$F$49),"#,##0")&")"&" – "&TEXT(MAX(Pivots!$F$40:$F$49)/Pivots!$F$50,"0.0%")&" of total sales" -> Mumbai (₹3,51,454) – 22.5% of total sales
B10: Weakest city | C10: =INDEX(Pivots!$A$40:$A$49,MATCH(MIN(Pivots!$F$40:$F$49),Pivots!$F$40:$F$49,0))&" (₹"&TEXT(MIN(Pivots!$F$40:$F$49),"#,##0")&")"&" – "&TEXT(MIN(Pivots!$F$40:$F$49)/Pivots!$F$50,"0.0%")&" of total sales" -> Jaipur (₹27,381) – 1.7% of total sales
B11: Most-used payment method (by sales) | C11: =INDEX(Pivots!$A$55:$A$59,MATCH(MAX(Pivots!$F$55:$F$59),Pivots!$F$55:$F$59,0))&" (₹"&TEXT(MAX(Pivots!$F$55:$F$59),"#,##0")&")"&" – "&TEXT(MAX(Pivots!$F$55:$F$59)/Pivots!$F$60,"0.0%")&" of total sales" -> UPI (₹5,52,508) – 35.3% of total sales
B12: Order status split | C12: ="Delivered "&TEXT(COUNTIFS(Cleaned_Data!$N$2:$N$501,"Delivered")/COUNTA(Cleaned_Data!$A$2:$A$501),"0.0%")&" | Cancelled "&TEXT(COUNTIFS(Cleaned_Data!$N$2:$N$501,"Cancelled")/COUNTA(Cleaned_Data!$A$2:$A$501),"0.0%")&" | Pending/Shipped "&TEXT(COUNTIFS(Cleaned_Data!$N$2:$N$501,"Pending")/COUNTA(Cleaned_Data!$A$2:$A$501),"0.0%") -> Delivered 76.4% | Cancelled 12.6% | Pending/Shipped 11.0%
B13: Delivered : Cancelled ratio | C13: =TEXT(COUNTIFS(Cleaned_Data!$N$2:$N$501,"Delivered")/COUNTIFS(Cleaned_Data!$N$2:$N$501,"Cancelled"),"0.0")&" delivered for every 1 cancelled order" -> 6.1 delivered for every 1 cancelled order
B14: Total sales lost to cancellations | C14: ="₹"&TEXT(SUMIFS(Cleaned_Data!$G$2:$G$501,Cleaned_Data!$N$2:$N$501,"Cancelled"),"#,##0")&" ("&TEXT(SUMIFS(Cleaned_Data!$G$2:$G$501,Cleaned_Data!$N$2:$N$501,"Cancelled")/SUM(Cleaned_Data!$G$2:$G$501),"0.0%")&" of gross sales)" -> ₹2,12,492 (13.6% of gross sales)
B15: Top customer | C15: =Pivots!$J$11&" – ₹"&TEXT(Pivots!$K$11,"#,##0") -> Anjali Verma – ₹59,983
B17: Recommendations
B18: 1. Keep top products and best category well stocked and advertised; they drive the largest share of revenue.
B19: 2. Investigate the weakest cities and categories – test local promotions, faster delivery options or price changes.
B20: 3. Reduce cancellations: review the cancelled orders by product/city, tighten stock accuracy and confirm Cash On Delivery orders before dispatch.
B21: 4. Follow up on Pending/Shipped orders so they convert to Delivered within the promised window.
B22: 5. Promote the most-used digital payment methods (e.g. UPI offers) and nudge COD customers to prepay.
B23: 6. Run loyalty / repeat-purchase offers for the top-10 customers who contribute a disproportionate share of sales.

Sheet README
B1: Amazon Sales Performance Analysis – Excel Project
B3: IMPORTANT – sample data | C3: The original Google Drive dataset could not be opened here, so Raw_Data contains a generated SAMPLE dataset (one month, Sep 2026, same columns as the case study + Payment Method and Order Status). To use your real data: paste it into Raw_Data (same column order, starting A2), then extend the Cleaned_Data formulas down to match the row count.
B4: Sheets | C4: Dashboard → KPIs, 6 charts, 4 dropdown filters (Category, Location, Order Status, Month) Pivots → Category, Product, City, Payment, Status, Customer summary tables + Top 10 customers Cleaned_Data → formula-cleaned copy of Raw_Data with calculated fields Raw_Data → data as received (duplicates, stray spaces, mixed case, wrong totals) Insights → auto-updating findings and recommendations
B5: Data cleaning done | C5: • Removed 15 duplicate orders (Raw_Data has 515 rows → Cleaned_Data has 500) • TRIM / PROPER applied to Product, Customer Name, Location, Status; TRIM on Order ID, Category, Payment • Dates stored as real dates; Price, Quantity, Total Sales as numbers • Total Sales recalculated as Price × Quantity; Validation column shows 'Corrected' where Raw_Data's total was wrong
B6: Calculated fields | C6: Month =TEXT(Date,"MMM") · Day of Week =TEXT(Date,"ddd") · Status Flag groups Shipped with Pending (Delivered / Cancelled / Pending)
B7: About the 'PivotTables' | C7: The summary tables on the Pivots sheet are built with SUMIFS/COUNTIFS so they are fully formula-driven and respond to the Dashboard dropdowns. If you want native PivotTables/Slicers, select Cleaned_Data → Insert → PivotTable and Insert → Slicer.
B8: Notes | C8: Total Sales includes all orders (also cancelled). Order Status table ignores the Status filter. 'All' = no filter. Yellow cells = inputs.
